Workbook
Name Societe: 'Accueil'!$C$6
Name Exercice: 'Accueil'!$C$12
Name Comptes: 'Plan comptable'!$H$8:$H$192
Name Journaux: 'Plan comptable'!$M$8:$M$13
Name Centres: 'Centres de coûts'!$A$8:$A$57

Sheet Accueil
A1: SYSTÈME COMPTABLE — SCF ALGÉRIE
A2: نظام محاسبي — النظام المحاسبي المالي الجزائري
A3: Plan comptable · Journal · Grand livre · Balance · Coût des ventes · Compte de résultat · Bilan
B5: IDENTIFICATION DE L'ENTREPRISE — تعريف المؤسسة
B6: Raison sociale | C6: Mon Entreprise SARL | E6: التسمية الاجتماعية
B7: NIF | E7: رقم التعريف الجبائي
B8: NIS | E8: رقم التعريف الإحصائي
B9: Registre de commerce | E9: السجل التجاري
B10: Article d'imposition | E10: المادة الجبائية
B11: Adresse | E11: العنوان
B12: Exercice | C12: 2026 | E12: السنة المالية
B13: Début d'exercice | C13: =DATE(Exercice,1,1) | E13: بداية السنة
B14: Fin d'exercice | C14: =DATE(Exercice,12,31) | E14: نهاية السنة
B16: LES FEUILLES — أوراق العمل
B17: → Plan comptable | D17: دليل الحسابات | E17: La nomenclature du SCF, classes 1 à 7, et vos propres subdivisions.
B18: → Centres de coûts | D18: مراكز التكلفة | E18: Magasin, chantier, véhicule : ce que vous voulez suivre à part.
B19: → Journal | D19: اليومية | E19: La seule feuille où l'on saisit. Une ligne par compte mouvementé.
B20: → Grand livre | D20: الأستاذ العام | E20: Le détail d'un compte, avec son solde qui court.
B21: → Balance | D21: ميزان المراجعة | E21: Mouvements et soldes de tous les comptes. Le contrôle d'équilibre.
B22: → Coût des ventes | D22: تكلفة المبيعات | E22: Ce que les ventes ont coûté, et ce qu'elles ont laissé.
B23: → Compte de résultat | D23: حساب النتائج | E23: Le compte de résultat par nature, avec ses soldes intermédiaires.
B24: → Bilan | D24: الميزانية | E24: Actif et passif à la clôture, présentation de l'arrêté de 2008.
B25: → Rapports | D25: التقارير | E25: TVA, trésorerie, tiers, charges par nature, résultat par centre.
B27: CONTRÔLES — المراقبة
B28: Total débit du journal | C28: =SUM('Journal'!$H$8:$H$2007)
B29: Total crédit du journal | C29: =SUM('Journal'!$I$8:$I$2007)
B30: Écart débit / crédit | C30: =SUM('Journal'!$H$8:$H$2007)-SUM('Journal'!$I$8:$I$2007)
B31: Résultat net de l'exercice | C31: ='Compte de résultat'!$D$36
B32: Total actif | C32: ='Bilan'!$E$29
B33: Total passif | C33: ='Bilan'!$E$53
B34: Écart actif / passif | C34: ='Bilan'!$E$29-'Bilan'!$E$53
B35: Le classeur est-il cohérent ? | C35: =IF(AND(ROUND(C30,2)=0,ROUND(C34,2)=0),"OUI — débit = crédit et actif = passif","NON — corrigez les écarts ci-dessus")
B37: MODE D'EMPLOI — طريقة الاستعمال
B38: 1. Renseignez l'entreprise et l'exercice ci-dessus. Tout le classeur en reprend le nom et l'année.
B39: 2. Ouvrez le Journal et saisissez vos écritures : une ligne par compte mouvementé, le débit à gauche, le crédit à droite. Le compte se choisit dans la liste déroulante.
B40: 3. Une écriture est équilibrée quand son débit égale son crédit. Le total du journal, en haut de la feuille, le dit à chaque instant.
B41: 4. Les dix lignes marquées EXEMPLE montrent une ouverture, une vente, un achat, un salaire, un amortissement et une déclaration de TVA. Supprimez-les avant de commencer.
B42: 5. Tout le reste se calcule seul. Aucune autre feuille n'attend de saisie, sauf les cellules jaunes du Coût des ventes.
B43: 6. Le plan comptable est modifiable : ajoutez vos subdivisions à la suite du tableau (4111 pour un client suivi à part, 6131 pour un local précis) et recopiez la formule des colonnes de droite.

Sheet Plan comptable
A1: PLAN COMPTABLE — SCF
A2: دليل الحسابات — النظام المحاسبي المالي
A3: =Societe&" · Exercice "&Exercice
A5: Arrêté du 26 juillet 2008. Les lignes grises sont des rubriques : on n'y passe pas d'écriture.
H6: Liste de saisie — ne pas trier ni supprimer
A7: Compte | B7: Intitulé | C7: التسمية | D7: Classe | E7: Type | F7: Rubrique du bilan | H7: Compte | I7: Intitulé | J7: Rubrique | K7: Déd. | M7: Journal | N7: Libellé
A8: 10 | B8: Capital, réserves et assimilés | C8: رأس المال والاحتياطات وما شابهها | D8: 1 | E8: Rubrique | H8: 101 | I8: Capital émis (capital social, fonds de dotation) | J8: CP_CAP | K8: 0 | M8: AN | N8: À-nouveaux
A9: 101 | B9: Capital émis (capital social, fonds de dotation) | C9: رأس المال الصادر (رأس المال الاجتماعي) | D9: 1 | E9: Compte | F9: CP_CAP | H9: 103 | I9: Primes liées au capital social | J9: CP_PRI | K9: 0 | M9: VE | N9: Ventes
A10: 103 | B10: Primes liées au capital social | C10: العلاوات المرتبطة برأس المال | D10: 1 | E10: Compte | F10: CP_PRI | H10: 104 | I10: Écart d'évaluation | J10: CP_PRI | K10: 0 | M10: AC | N10: Achats
A11: 104 | B11: Écart d'évaluation | C11: فارق التقييم | D11: 1 | E11: Compte | F11: CP_PRI | H11: 105 | I11: Écart de réévaluation | J11: CP_REE | K11: 0 | M11: BQ | N11: Banque
A12: 105 | B12: Écart de réévaluation | C12: فارق إعادة التقييم | D12: 1 | E12: Compte | F12: CP_REE | H12: 106 | I12: Réserves (légale, statutaire, ordinaire, réglementée) | J12: CP_PRI | K12: 0 | M12: CA | N12: Caisse
A13: 106 | B13: Réserves (légale, statutaire, ordinaire, réglementée) | C13: الاحتياطات (قانونية، نظامية، عادية، منظمة) | D13: 1 | E13: Compte | F13: CP_PRI | H13: 107 | I13: Écart d'équivalence | J13: CP_EQU | K13: 0 | M13: OD | N13: Opérations diverses
A14: 107 | B14: Écart d'équivalence | C14: فارق المعادلة | D14: 1 | E14: Compte | F14: CP_EQU | H14: 108 | I14: Compte de l'exploitant | J14: CP_ART | K14: 0
A15: 108 | B15: Compte de l'exploitant | C15: حساب المستغل | D15: 1 | E15: Compte | F15: CP_ART | H15: 109 | I15: Capital souscrit non appelé | J15: CP_NAP | K15: 0
A16: 109 | B16: Capital souscrit non appelé | C16: رأس المال المكتتب غير المستدعى | D16: 1 | E16: Compte | F16: CP_NAP | H16: 110 | I16: Report à nouveau (solde créditeur) | J16: CP_ART | K16: 0
A17: 11 | B17: Report à nouveau | C17: الترحيل من جديد | D17: 1 | E17: Rubrique | H17: 119 | I17: Report à nouveau (solde débiteur) | J17: CP_ART | K17: 0
A18: 110 | B18: Report à nouveau (solde créditeur) | C18: الترحيل من جديد (رصيد دائن) | D18: 1 | E18: Compte | F18: CP_ART | H18: 120 | I18: Résultat de l'exercice (bénéfice) | J18: CP_RES | K18: 0
A19: 119 | B19: Report à nouveau (solde débiteur) | C19: الترحيل من جديد (رصيد مدين) | D19: 1 | E19: Compte | F19: CP_ART | H19: 129 | I19: Résultat de l'exercice (perte) | J19: CP_RES | K19: 0
A20: 12 | B20: Résultat de l'exercice | C20: نتيجة السنة المالية | D20: 1 | E20: Rubrique | H20: 131 | I20: Subventions d'équipement | J20: PN_AUT | K20: 0
A21: 120 | B21: Résultat de l'exercice (bénéfice) | C21: نتيجة السنة المالية (ربح) | D21: 1 | E21: Compte | F21: CP_RES | H21: 133 | I21: Impôts différés actif | J21: AN_IDA | K21: 0
A22: 129 | B22: Résultat de l'exercice (perte) | C22: نتيجة السنة المالية (خسارة) | D22: 1 | E22: Compte | F22: CP_RES | H22: 134 | I22: Impôts différés passif | J22: PN_IDP | K22: 0
A23: 13 | B23: Produits et charges différés | C23: المنتوجات والأعباء المؤجلة | D23: 1 | E23: Rubrique | H23: 138 | I23: Autres produits et charges différés | J23: PN_AUT | K23: 0
A24: 131 | B24: Subventions d'équipement | C24: إعانات التجهيز | D24: 1 | E24: Compte | F24: PN_AUT | H24: 153 | I24: Provisions pour pensions et obligations similaires | J24: PN_PRO | K24: 0
A25: 133 | B25: Impôts différés actif | C25: الضرائب المؤجلة على الأصول | D25: 1 | E25: Compte | F25: AN_IDA | H25: 155 | I25: Provisions pour impôts | J25: PN_IDP | K25: 0
A26: 134 | B26: Impôts différés passif | C26: الضرائب المؤجلة على الخصوم | D26: 1 | E26: Compte | F26: PN_IDP | H26: 156 | I26: Provisions pour renouvellement des immobilisations | J26: PN_PRO | K26: 0
A27: 138 | B27: Autres produits et charges différés | C27: منتوجات وأعباء مؤجلة أخرى | D27: 1 | E27: Compte | F27: PN_AUT | H27: 158 | I27: Autres provisions pour charges | J27: PN_PRO | K27: 0
A28: 15 | B28: Provisions pour charges — passifs non courants | C28: مؤونات الأعباء — خصوم غير جارية | D28: 1 | E28: Rubrique | H28: 161 | I28: Titres participatifs | J28: PN_EMP | K28: 0
A29: 153 | B29: Provisions pour pensions et obligations similaires | C29: مؤونات المعاشات والالتزامات المماثلة | D29: 1 | E29: Compte | F29: PN_PRO | H29: 163 | I29: Autres emprunts obligataires | J29: PN_EMP | K29: 0
A30: 155 | B30: Provisions pour impôts | C30: مؤونات الضرائب | D30: 1 | E30: Compte | F30: PN_IDP | H30: 164 | I30: Emprunts auprès des établissements de crédit | J30: PN_EMP | K30: 0
A31: 156 | B31: Provisions pour renouvellement des immobilisations | C31: مؤونات تجديد التثبيتات | D31: 1 | E31: Compte | F31: PN_PRO | H31: 165 | I31: Dépôts et cautionnements reçus | J31: PN_AUT | K31: 0
A32: 158 | B32: Autres provisions pour charges | C32: مؤونات أخرى للأعباء | D32: 1 | E32: Compte | F32: PN_PRO | H32: 167 | I32: Dettes sur contrat de location-financement | J32: PN_EMP | K32: 0
A33: 16 | B33: Emprunts et dettes assimilées | C33: الاقتراضات والديون المماثلة | D33: 1 | E33: Rubrique | H33: 168 | I33: Autres emprunts et dettes assimilées | J33: PN_EMP | K33: 0
A34: 161 | B34: Titres participatifs | C34: سندات المساهمة | D34: 1 | E34: Compte | F34: PN_EMP | H34: 17 | I34: Dettes rattachées à des participations | J34: PN_EMP | K34: 0
A35: 163 | B35: Autres emprunts obligataires | C35: اقتراضات سندية أخرى | D35: 1 | E35: Compte | F35: PN_EMP | H35: 203 | I35: Frais de développement immobilisables | J35: AN_INC | K35: 0
A36: 164 | B36: Emprunts auprès des établissements de crédit | C36: الاقتراضات لدى مؤسسات القرض | D36: 1 | E36: Compte | F36: PN_EMP | H36: 204 | I36: Logiciels informatiques et assimilés | J36: AN_INC | K36: 0
A37: 165 | B37: Dépôts et cautionnements reçus | C37: الودائع والكفالات المقبوضة | D37: 1 | E37: Compte | F37: PN_AUT | H37: 205 | I37: Concessions, brevets, licences, marques | J37: AN_INC | K37: 0
A38: 167 | B38: Dettes sur contrat de location-financement | C38: ديون عقد الإيجار التمويلي | D38: 1 | E38: Compte | F38: PN_EMP | H38: 207 | I38: Écart d'acquisition (goodwill) | J38: AN_GW | K38: 0
A39: 168 | B39: Autres emprunts et dettes assimilées | C39: اقتراضات وديون مماثلة أخرى | D39: 1 | E39: Compte | F39: PN_EMP | H39: 208 | I39: Autres immobilisations incorporelles | J39: AN_INC | K39: 0
A40: 17 | B40: Dettes rattachées à des participations | C40: الديون الملحقة بمساهمات | D40: 1 | E40: Compte | F40: PN_EMP | H40: 211 | I40: Terrains | J40: AN_TER | K40: 0
A41: 20 | B41: Immobilisations incorporelles | C41: التثبيتات المعنوية | D41: 2 | E41: Rubrique | H41: 212 | I41: Agencements et aménagements de terrain | J41: AN_AUT | K41: 0
A42: 203 | B42: Frais de développement immobilisables | C42: مصاريف التطوير القابلة للتثبيت | D42: 2 | E42: Compte | F42: AN_INC | H42: 213 | I42: Constructions | J42: AN_BAT | K42: 0
A43: 204 | B43: Logiciels informatiques et assimilés | C43: برمجيات المعلوماتية وما شابهها | D43: 2 | E43: Compte | F43: AN_INC | H43: 215 | I43: Installations techniques, matériel et outillage | J43: AN_AUT | K43: 0
A44: 205 | B44: Concessions, brevets, licences, marques | C44: الامتيازات وبراءات الاختراع والرخص والعلامات | D44: 2 | E44: Compte | F44: AN_INC | H44: 218 | I44: Autres immobilisations corporelles | J44: AN_AUT | K44: 0
A45: 207 | B45: Écart d'acquisition (goodwill) | C45: فارق الشراء | D45: 2 | E45: Compte | F45: AN_GW | H45: 2182 | I45: Matériel de transport | J45: AN_AUT | K45: 0
A46: 208 | B46: Autres immobilisations incorporelles | C46: تثبيتات معنوية أخرى | D46: 2 | E46: Compte | F46: AN_INC | H46: 2183 | I46: Matériel de bureau et informatique | J46: AN_AUT | K46: 0
A47: 21 | B47: Immobilisations corporelles | C47: التثبيتات العينية | D47: 2 | E47: Rubrique | H47: 2184 | I47: Mobilier | J47: AN_AUT | K47: 0
A48: 211 | B48: Terrains | C48: الأراضي | D48: 2 | E48: Compte | F48: AN_TER | H48: 22 | I48: Immobilisations en concession | J48: AN_CONC | K48: 0
A49: 212 | B49: Agencements et aménagements de terrain | C49: تهيئة وترتيب الأراضي | D49: 2 | E49: Compte | F49: AN_AUT | H49: 232 | I49: Immobilisations corporelles en cours | J49: AN_ENC | K49: 0
A50: 213 | B50: Constructions | C50: المباني | D50: 2 | E50: Compte | F50: AN_BAT | H50: 237 | I50: Immobilisations incorporelles en cours | J50: AN_ENC | K50: 0
A51: 215 | B51: Installations techniques, matériel et outillage | C51: المنشآت التقنية والمعدات والأدوات | D51: 2 | E51: Compte | F51: AN_AUT | H51: 261 | I51: Titres de filiales | J51: AN_FIN | K51: 0
A52: 218 | B52: Autres immobilisations corporelles | C52: تثبيتات عينية أخرى | D52: 2 | E52: Compte | F52: AN_AUT | H52: 265 | I52: Titres mis en équivalence | J52: AN_FIN | K52: 0
A53: 2182 | B53: Matériel de transport | C53: معدات النقل | D53: 2 | E53: Compte | F53: AN_AUT | H53: 274 | I53: Prêts et créances sur contrat de location-financement | J53: AN_PRET | K53: 0
A54: 2183 | B54: Matériel de bureau et informatique | C54: معدات المكتب والإعلام الآلي | D54: 2 | E54: Compte | F54: AN_AUT | H54: 275 | I54: Dépôts et cautionnements versés | J54: AN_PRET | K54: 0
A55: 2184 | B55: Mobilier | C55: الأثاث | D55: 2 | E55: Compte | F55: AN_AUT | H55: 280 | I55: Amortissement des immobilisations incorporelles | J55: AN_INC | K55: 1
A56: 22 | B56: Immobilisations en concession | C56: التثبيتات الممنوحة في شكل امتياز | D56: 2 | E56: Compte | F56: AN_CONC | H56: 281 | I56: Amortissement des immobilisations corporelles | J56: AN_AUT | K56: 1
A57: 23 | B57: Immobilisations en cours | C57: التثبيتات الجاري إنجازها | D57: 2 | E57: Rubrique | H57: 2813 | I57: Amortissement des constructions | J57: AN_BAT | K57: 1
A58: 232 | B58: Immobilisations corporelles en cours | C58: تثبيتات عينية جاري إنجازها | D58: 2 | E58: Compte | F58: AN_ENC | H58: 2818 | I58: Amortissement des autres immobilisations corporelles | J58: AN_AUT | K58: 1
A59: 237 | B59: Immobilisations incorporelles en cours | C59: تثبيتات معنوية جاري إنجازها | D59: 2 | E59: Compte | F59: AN_ENC | H59: 29 | I59: Pertes de valeur sur immobilisations | J59: AN_AUT | K59: 1
A60: 26 | B60: Participations et créances rattachées | C60: المساهمات والديون الملحقة بها | D60: 2 | E60: Rubrique | H60: 30 | I60: Stocks de marchandises | J60: AC_STK | K60: 0
A61: 261 | B61: Titres de filiales | C61: سندات الفروع | D61: 2 | E61: Compte | F61: AN_FIN | H61: 31 | I61: Matières premières et fournitures | J61: AC_STK | K61: 0
A62: 265 | B62: Titres mis en équivalence | C62: السندات الموضوعة موضع المعادلة | D62: 2 | E62: Compte | F62: AN_FIN | H62: 32 | I62: Autres approvisionnements | J62: AC_STK | K62: 0
A63: 27 | B63: Autres immobilisations financières | C63: تثبيتات مالية أخرى | D63: 2 | E63: Rubrique | H63: 33 | I63: En-cours de production de biens | J63: AC_STK | K63: 0
A64: 274 | B64: Prêts et créances sur contrat de location-financement | C64: القروض والديون على عقد الإيجار التمويلي | D64: 2 | E64: Compte | F64: AN_PRET | H64: 34 | I64: En-cours de production de services | J64: AC_STK | K64: 0
A65: 275 | B65: Dépôts et cautionnements versés | C65: الودائع والكفالات المدفوعة | D65: 2 | E65: Compte | F65: AN_PRET | H65: 35 | I65: Stocks de produits finis | J65: AC_STK | K65: 0
A66: 28 | B66: Amortissement des immobilisations | C66: اهتلاك التثبيتات | D66: 2 | E66: Rubrique | H66: 36 | I66: Stocks provenant d'immobilisations | J66: AC_STK | K66: 0
A67: 280 | B67: Amortissement des immobilisations incorporelles | C67: اهتلاك التثبيتات المعنوية | D67: 2 | E67: Compte | F67: AN_INC | H67: 37 | I67: Stocks à l'extérieur (en consignation, en dépôt) | J67: AC_STK | K67: 0
A68: 281 | B68: Amortissement des immobilisations corporelles | C68: اهتلاك التثبيتات العينية | D68: 2 | E68: Compte | F68: AN_AUT | H68: 38 | I68: Achats stockés | J68: AC_STK | K68: 0
A69: 2813 | B69: Amortissement des constructions | C69: اهتلاك المباني | D69: 2 | E69: Compte | F69: AN_BAT | H69: 39 | I69: Pertes de valeur sur stocks et en-cours | J69: AC_STK | K69: 1
A70: 2818 | B70: Amortissement des autres immobilisations corporelles | C70: اهتلاك التثبيتات العينية الأخرى | D70: 2 | E70: Compte | F70: AN_AUT | H70: 401 | I70: Fournisseurs de stocks et services | J70: PC_FRN | K70: 0
A71: 29 | B71: Pertes de valeur sur immobilisations | C71: خسائر القيمة عن التثبيتات | D71: 2 | E71: Compte | F71: AN_AUT | H71: 403 | I71: Fournisseurs, effets à payer | J71: PC_FRN | K71: 0
A72: 30 | B72: Stocks de marchandises | C72: مخزونات البضائع | D72: 3 | E72: Compte | F72: AC_STK | H72: 404 | I72: Fournisseurs d'immobilisations | J72: PC_FRN | K72: 0
A73: 31 | B73: Matières premières et fournitures | C73: المواد الأولية واللوازم | D73: 3 | E73: Compte | F73: AC_STK | H73: 408 | I73: Fournisseurs, factures non parvenues | J73: PC_FRN | K73: 0
A74: 32 | B74: Autres approvisionnements | C74: تموينات أخرى | D74: 3 | E74: Compte | F74: AC_STK | H74: 409 | I74: Fournisseurs débiteurs (avances, acomptes) | J74: AC_DEB | K74: 0
A75: 33 | B75: En-cours de production de biens | C75: منتجات قيد التنفيذ — سلع | D75: 3 | E75: Compte | F75: AC_STK | H75: 411 | I75: Clients | J75: AC_CLI | K75: 0
A76: 34 | B76: En-cours de production de services | C76: منتجات قيد التنفيذ — خدمات | D76: 3 | E76: Compte | F76: AC_STK | H76: 413 | I76: Clients, effets à recevoir | J76: AC_CLI | K76: 0
A77: 35 | B77: Stocks de produits finis | C77: مخزونات المنتجات التامة | D77: 3 | E77: Compte | F77: AC_STK | H77: 416 | I77: Clients douteux ou litigieux | J77: AC_CLI | K77: 0
A78: 36 | B78: Stocks provenant d'immobilisations | C78: مخزونات متأتية من التثبيتات | D78: 3 | E78: Compte | F78: AC_STK | H78: 417 | I78: Créances sur travaux ou prestations en cours | J78: AC_CLI | K78: 0
... A81: 39 | B81: Pertes de valeur sur stocks et en-cours | C81: خسائر القيمة عن المخزونات | D81: 3 | E81: Compte | F81: AC_STK | H81: 421 | I81: Personnel, rémunérations dues | J81: PC_AUT | K81: 0
A82: 40 | B82: Fournisseurs et comptes rattachés | C82: الموردون والحسابات الملحقة | D82: 4 | E82: Rubrique | H82: 422 | I82: Fonds des œuvres sociales | J82: PC_AUT | K82: 0
A83: 401 | B83: Fournisseurs de stocks et services | C83: موردو المخزونات والخدمات | D83: 4 | E83: Compte | F83: PC_FRN | H83: 425 | I83: Personnel, avances et acomptes accordés | J83: AC_DEB | K83: 0
A84: 403 | B84: Fournisseurs, effets à payer | C84: الموردون، أوراق الدفع | D84: 4 | E84: Compte | F84: PC_FRN | H84: 428 | I84: Personnel, charges à payer | J84: PC_AUT | K84: 0
A85: 404 | B85: Fournisseurs d'immobilisations | C85: موردو التثبيتات | D85: 4 | E85: Compte | F85: PC_FRN | H85: 431 | I85: Sécurité sociale (CNAS) | J85: PC_AUT | K85: 0
A86: 408 | B86: Fournisseurs, factures non parvenues | C86: الموردون، فواتير لم تصل بعد | D86: 4 | E86: Compte | F86: PC_FRN | H86: 432 | I86: Autres organismes sociaux (CASNOS, CACOBATPH) | J86: PC_AUT | K86: 0
A87: 409 | B87: Fournisseurs débiteurs (avances, acomptes) | C87: الموردون المدينون (تسبيقات ودفعات) | D87: 4 | E87: Compte | F87: AC_DEB | H87: 438 | I87: Organismes sociaux, charges à payer | J87: PC_AUT | K87: 0
A88: 41 | B88: Clients et comptes rattachés | C88: الزبائن والحسابات الملحقة | D88: 4 | E88: Rubrique | H88: 441 | I88: État, subventions à recevoir | J88: AC_DEB | K88: 0
A89: 411 | B89: Clients | C89: الزبائن | D89: 4 | E89: Compte | F89: AC_CLI | H89: 442 | I89: État, impôts et taxes recouvrables sur des tiers | J89: PC_IMP | K89: 0
A90: 413 | B90: Clients, effets à recevoir | C90: الزبائن، أوراق القبض | D90: 4 | E90: Compte | F90: AC_CLI | H90: 444 | I90: État, impôts sur les résultats (IBS, IRG) | J90: PC_IMP | K90: 0
A91: 416 | B91: Clients douteux ou litigieux | C91: الزبائن المشكوك فيهم | D91: 4 | E91: Compte | F91: AC_CLI | H91: 44562 | I91: TVA déductible sur immobilisations | J91: AC_IMP | K91: 0
A92: 417 | B92: Créances sur travaux ou prestations en cours | C92: ديون على أشغال أو خدمات قيد التنفيذ | D92: 4 | E92: Compte | F92: AC_CLI | H92: 44566 | I92: TVA déductible sur biens et services | J92: AC_IMP | K92: 0
A93: 418 | B93: Clients, produits non encore facturés | C93: الزبائن، منتوجات لم تفوتر بعد | D93: 4 | E93: Compte | F93: AC_CLI | H93: 4457 | I93: TVA collectée | J93: PC_IMP | K93: 0
A94: 419 | B94: Clients créditeurs (avances reçues) | C94: الزبائن الدائنون (تسبيقات مقبوضة) | D94: 4 | E94: Compte | F94: PC_AUT | H94: 4458 | I94: TVA à régulariser ou en attente | J94: PC_IMP | K94: 0
A95: 42 | B95: Personnel et comptes rattachés | C95: المستخدمون والحسابات الملحقة | D95: 4 | E95: Rubrique | H95: 4459 | I95: TVA à décaisser | J95: PC_IMP | K95: 0
A96: 421 | B96: Personnel, rémunérations dues | C96: المستخدمون، الأجور المستحقة | D96: 4 | E96: Compte | F96: PC_AUT | H96: 447 | I96: Autres impôts, taxes et versements assimilés (TAP) | J96: PC_IMP | K96: 0
A97: 422 | B97: Fonds des œuvres sociales | C97: صندوق الخدمات الاجتماعية | D97: 4 | E97: Compte | F97: PC_AUT | H97: 448 | I97: État, charges à payer et produits à recevoir | J97: PC_IMP | K97: 0
A98: 425 | B98: Personnel, avances et acomptes accordés | C98: المستخدمون، تسبيقات ودفعات ممنوحة | D98: 4 | E98: Compte | F98: AC_DEB | H98: 45 | I98: Groupe et associés | J98: PC_AUT | K98: 0
A99: 428 | B99: Personnel, charges à payer | C99: المستخدمون، أعباء واجبة الدفع | D99: 4 | E99: Compte | F99: PC_AUT | H99: 462 | I99: Créances sur cessions d'immobilisations | J99: AC_DEB | K99: 0
A100: 43 | B100: Organismes sociaux et comptes rattachés | C100: الهيئات الاجتماعية والحسابات الملحقة | D100: 4 | E100: Rubrique | H100: 467 | I100: Autres comptes débiteurs ou créditeurs | J100: AC_DEB | K100: 0
A101: 431 | B101: Sécurité sociale (CNAS) | C101: الضمان الاجتماعي (CNAS) | D101: 4 | E101: Compte | F101: PC_AUT | H101: 468 | I101: Créditeurs divers | J101: PC_AUT | K101: 0
A102: 432 | B102: Autres organismes sociaux (CASNOS, CACOBATPH) | C102: هيئات اجتماعية أخرى (CASNOS) | D102: 4 | E102: Compte | F102: PC_AUT | H102: 47 | I102: Comptes transitoires ou d'attente | J102: AC_AUT | K102: 0
A103: 438 | B103: Organismes sociaux, charges à payer | C103: الهيئات الاجتماعية، أعباء واجبة الدفع | D103: 4 | E103: Compte | F103: PC_AUT | H103: 486 | I103: Charges constatées d'avance | J103: AC_AUT | K103: 0
...

Sheet Centres de coûts
A1: CENTRES DE COÛTS
A2: مراكز التكلفة
A3: =Societe&" · Exercice "&Exercice
A5: Un centre s'affecte sur une ligne du journal, colonne G. Les charges et les produits qui le portent se retrouvent dans Rapports.
A7: Code | B7: Libellé | C7: التسمية | D7: Note
A8: MAG1 | B8: Magasin centre | C8: المحل المركزي | D8: EXEMPLE
A9: CH01 | B9: Chantier Alger | C9: ورشة الجزائر | D9: EXEMPLE
A10: VEH1 | B10: Véhicule utilitaire | C10: سيارة النفعية | D10: EXEMPLE

Sheet Journal
A1: JOURNAL GÉNÉRAL
A2: اليومية العامة
A3: =Societe&" · Exercice "&Exercice
A5: Une ligne par compte mouvementé. Un montant en débit OU en crédit, jamais les deux. La colonne Contrôle signale ce qui cloche.
A6: TOTAUX | H6: =SUM(H8:H2007) | I6: =SUM(I8:I2007) | J6: =IF(ROUND($H$6-$I$6,2)=0,"Équilibré","Écart : "&TEXT($H$6-$I$6,"#,##0.00"))
A7: Date | B7: Journal | C7: N° pièce | D7: Compte | E7: Intitulé du compte | F7: Libellé de l'opération | G7: Centre | H7: Débit | I7: Crédit | J7: Contrôle
A8: 46023 | B8: AN | C8: AN-2026 | D8: 2183 | E8: =IF($D8="","",IFERROR(VLOOKUP($D8,'Plan comptable'!$H:$I,2,FALSE),"compte hors plan")) | F8: Matériel informatique · EXEMPLE | H8: 80000 | J8: =IF($D8="","",IF(AND($H8<>"",$I8<>""),"débit ET crédit",IF(AND($H8="",$I8=""),"montant manquant",IF(ISNA(MATCH($D8,'Plan comptable'!$H:$H,0)),"compte hors plan",IF(AND($A8<>"",YEAR($A8)<>Exercice),"hors exercice","")))))
A9: 46023 | B9: AN | C9: AN-2026 | D9: 30 | E9: =IF($D9="","",IFERROR(VLOOKUP($D9,'Plan comptable'!$H:$I,2,FALSE),"compte hors plan")) | F9: Stock de marchandises au 01/01 · EXEMPLE | H9: 300000 | J9: =IF($D9="","",IF(AND($H9<>"",$I9<>""),"débit ET crédit",IF(AND($H9="",$I9=""),"montant manquant",IF(ISNA(MATCH($D9,'Plan comptable'!$H:$H,0)),"compte hors plan",IF(AND($A9<>"",YEAR($A9)<>Exercice),"hors exercice","")))))
A10: 46023 | B10: AN | C10: AN-2026 | D10: 512 | E10: =IF($D10="","",IFERROR(VLOOKUP($D10,'Plan comptable'!$H:$I,2,FALSE),"compte hors plan")) | F10: Solde bancaire au 01/01 · EXEMPLE | H10: 120000 | J10: =IF($D10="","",IF(AND($H10<>"",$I10<>""),"débit ET crédit",IF(AND($H10="",$I10=""),"montant manquant",IF(ISNA(MATCH($D10,'Plan comptable'!$H:$H,0)),"compte hors plan",IF(AND($A10<>"",YEAR($A10)<>Exercice),"hors exercice","")))))
A11: 46023 | B11: AN | C11: AN-2026 | D11: 101 | E11: =IF($D11="","",IFERROR(VLOOKUP($D11,'Plan comptable'!$H:$I,2,FALSE),"compte hors plan")) | F11: Capital · EXEMPLE | I11: 500000 | J11: =IF($D11="","",IF(AND($H11<>"",$I11<>""),"débit ET crédit",IF(AND($H11="",$I11=""),"montant manquant",IF(ISNA(MATCH($D11,'Plan comptable'!$H:$H,0)),"compte hors plan",IF(AND($A11<>"",YEAR($A11)<>Exercice),"hors exercice","")))))
A12: 46027 | B12: VE | C12: FAC-2026-001 | D12: 411 | E12: =IF($D12="","",IFERROR(VLOOKUP($D12,'Plan comptable'!$H:$I,2,FALSE),"compte hors plan")) | F12: SARL Atlas — facture 001 · EXEMPLE | G12: MAG1 | H12: 119000 | J12: =IF($D12="","",IF(AND($H12<>"",$I12<>""),"débit ET crédit",IF(AND($H12="",$I12=""),"montant manquant",IF(ISNA(MATCH($D12,'Plan comptable'!$H:$H,0)),"compte hors plan",IF(AND($A12<>"",YEAR($A12)<>Exercice),"hors exercice","")))))
A13: 46027 | B13: VE | C13: FAC-2026-001 | D13: 700 | E13: =IF($D13="","",IFERROR(VLOOKUP($D13,'Plan comptable'!$H:$I,2,FALSE),"compte hors plan")) | F13: Vente de marchandises · EXEMPLE | G13: MAG1 | I13: 100000 | J13: =IF($D13="","",IF(AND($H13<>"",$I13<>""),"débit ET crédit",IF(AND($H13="",$I13=""),"montant manquant",IF(ISNA(MATCH($D13,'Plan comptable'!$H:$H,0)),"compte hors plan",IF(AND($A13<>"",YEAR($A13)<>Exercice),"hors exercice","")))))
A14: 46027 | B14: VE | C14: FAC-2026-001 | D14: 4457 | E14: =IF($D14="","",IFERROR(VLOOKUP($D14,'Plan comptable'!$H:$I,2,FALSE),"compte hors plan")) | F14: TVA collectée 19 % · EXEMPLE | G14: MAG1 | I14: 19000 | J14: =IF($D14="","",IF(AND($H14<>"",$I14<>""),"débit ET crédit",IF(AND($H14="",$I14=""),"montant manquant",IF(ISNA(MATCH($D14,'Plan comptable'!$H:$H,0)),"compte hors plan",IF(AND($A14<>"",YEAR($A14)<>Exercice),"hors exercice","")))))
A15: 46042 | B15: BQ | C15: REG-001 | D15: 512 | E15: =IF($D15="","",IFERROR(VLOOKUP($D15,'Plan comptable'!$H:$I,2,FALSE),"compte hors plan")) | F15: Virement reçu — facture 001 · EXEMPLE | H15: 119000 | J15: =IF($D15="","",IF(AND($H15<>"",$I15<>""),"débit ET crédit",IF(AND($H15="",$I15=""),"montant manquant",IF(ISNA(MATCH($D15,'Plan comptable'!$H:$H,0)),"compte hors plan",IF(AND($A15<>"",YEAR($A15)<>Exercice),"hors exercice","")))))
A16: 46042 | B16: BQ | C16: REG-001 | D16: 411 | E16: =IF($D16="","",IFERROR(VLOOKUP($D16,'Plan comptable'!$H:$I,2,FALSE),"compte hors plan")) | F16: SARL Atlas · EXEMPLE | I16: 119000 | J16: =IF($D16="","",IF(AND($H16<>"",$I16<>""),"débit ET crédit",IF(AND($H16="",$I16=""),"montant manquant",IF(ISNA(MATCH($D16,'Plan comptable'!$H:$H,0)),"compte hors plan",IF(AND($A16<>"",YEAR($A16)<>Exercice),"hors exercice","")))))
A17: 46029 | B17: AC | C17: FA-FRS-014 | D17: 600 | E17: =IF($D17="","",IFERROR(VLOOKUP($D17,'Plan comptable'!$H:$I,2,FALSE),"compte hors plan")) | F17: Achat de marchandises · EXEMPLE | G17: MAG1 | H17: 60000 | J17: =IF($D17="","",IF(AND($H17<>"",$I17<>""),"débit ET crédit",IF(AND($H17="",$I17=""),"montant manquant",IF(ISNA(MATCH($D17,'Plan comptable'!$H:$H,0)),"compte hors plan",IF(AND($A17<>"",YEAR($A17)<>Exercice),"hors exercice","")))))
A18: 46029 | B18: AC | C18: FA-FRS-014 | D18: 44566 | E18: =IF($D18="","",IFERROR(VLOOKUP($D18,'Plan comptable'!$H:$I,2,FALSE),"compte hors plan")) | F18: TVA déductible 19 % · EXEMPLE | G18: MAG1 | H18: 11400 | J18: =IF($D18="","",IF(AND($H18<>"",$I18<>""),"débit ET crédit",IF(AND($H18="",$I18=""),"montant manquant",IF(ISNA(MATCH($D18,'Plan comptable'!$H:$H,0)),"compte hors plan",IF(AND($A18<>"",YEAR($A18)<>Exercice),"hors exercice","")))))
A19: 46029 | B19: AC | C19: FA-FRS-014 | D19: 401 | E19: =IF($D19="","",IFERROR(VLOOKUP($D19,'Plan comptable'!$H:$I,2,FALSE),"compte hors plan")) | F19: Fournisseur Sahara · EXEMPLE | G19: MAG1 | I19: 71400 | J19: =IF($D19="","",IF(AND($H19<>"",$I19<>""),"débit ET crédit",IF(AND($H19="",$I19=""),"montant manquant",IF(ISNA(MATCH($D19,'Plan comptable'!$H:$H,0)),"compte hors plan",IF(AND($A19<>"",YEAR($A19)<>Exercice),"hors exercice","")))))
A20: 46047 | B20: BQ | C20: REG-002 | D20: 401 | E20: =IF($D20="","",IFERROR(VLOOKUP($D20,'Plan comptable'!$H:$I,2,FALSE),"compte hors plan")) | F20: Règlement fournisseur Sahara · EXEMPLE | H20: 71400 | J20: =IF($D20="","",IF(AND($H20<>"",$I20<>""),"débit ET crédit",IF(AND($H20="",$I20=""),"montant manquant",IF(ISNA(MATCH($D20,'Plan comptable'!$H:$H,0)),"compte hors plan",IF(AND($A20<>"",YEAR($A20)<>Exercice),"hors exercice","")))))
A21: 46047 | B21: BQ | C21: REG-002 | D21: 512 | E21: =IF($D21="","",IFERROR(VLOOKUP($D21,'Plan comptable'!$H:$I,2,FALSE),"compte hors plan")) | F21: Virement émis · EXEMPLE | I21: 71400 | J21: =IF($D21="","",IF(AND($H21<>"",$I21<>""),"débit ET crédit",IF(AND($H21="",$I21=""),"montant manquant",IF(ISNA(MATCH($D21,'Plan comptable'!$H:$H,0)),"compte hors plan",IF(AND($A21<>"",YEAR($A21)<>Exercice),"hors exercice","")))))
A22: 46053 | B22: AC | C22: LOY-01 | D22: 613 | E22: =IF($D22="","",IFERROR(VLOOKUP($D22,'Plan comptable'!$H:$I,2,FALSE),"compte hors plan")) | F22: Loyer du local — janvier · EXEMPLE | G22: MAG1 | H22: 25000 | J22: =IF($D22="","",IF(AND($H22<>"",$I22<>""),"débit ET crédit",IF(AND($H22="",$I22=""),"montant manquant",IF(ISNA(MATCH($D22,'Plan comptable'!$H:$H,0)),"compte hors plan",IF(AND($A22<>"",YEAR($A22)<>Exercice),"hors exercice","")))))
A23: 46053 | B23: AC | C23: LOY-01 | D23: 512 | E23: =IF($D23="","",IFERROR(VLOOKUP($D23,'Plan comptable'!$H:$I,2,FALSE),"compte hors plan")) | F23: Loyer du local — janvier · EXEMPLE | G23: MAG1 | I23: 25000 | J23: =IF($D23="","",IF(AND($H23<>"",$I23<>""),"débit ET crédit",IF(AND($H23="",$I23=""),"montant manquant",IF(ISNA(MATCH($D23,'Plan comptable'!$H:$H,0)),"compte hors plan",IF(AND($A23<>"",YEAR($A23)<>Exercice),"hors exercice","")))))
A24: 46053 | B24: OD | C24: PAIE-01 | D24: 631 | E24: =IF($D24="","",IFERROR(VLOOKUP($D24,'Plan comptable'!$H:$I,2,FALSE),"compte hors plan")) | F24: Salaires de janvier · EXEMPLE | G24: MAG1 | H24: 45000 | J24: =IF($D24="","",IF(AND($H24<>"",$I24<>""),"débit ET crédit",IF(AND($H24="",$I24=""),"montant manquant",IF(ISNA(MATCH($D24,'Plan comptable'!$H:$H,0)),"compte hors plan",IF(AND($A24<>"",YEAR($A24)<>Exercice),"hors exercice","")))))
A25: 46053 | B25: OD | C25: PAIE-01 | D25: 431 | E25: =IF($D25="","",IFERROR(VLOOKUP($D25,'Plan comptable'!$H:$I,2,FALSE),"compte hors plan")) | F25: CNAS part salariale · EXEMPLE | G25: MAG1 | I25: 9000 | J25: =IF($D25="","",IF(AND($H25<>"",$I25<>""),"débit ET crédit",IF(AND($H25="",$I25=""),"montant manquant",IF(ISNA(MATCH($D25,'Plan comptable'!$H:$H,0)),"compte hors plan",IF(AND($A25<>"",YEAR($A25)<>Exercice),"hors exercice","")))))
A26: 46053 | B26: OD | C26: PAIE-01 | D26: 421 | E26: =IF($D26="","",IFERROR(VLOOKUP($D26,'Plan comptable'!$H:$I,2,FALSE),"compte hors plan")) | F26: Net à payer au personnel · EXEMPLE | G26: MAG1 | I26: 36000 | J26: =IF($D26="","",IF(AND($H26<>"",$I26<>""),"débit ET crédit",IF(AND($H26="",$I26=""),"montant manquant",IF(ISNA(MATCH($D26,'Plan comptable'!$H:$H,0)),"compte hors plan",IF(AND($A26<>"",YEAR($A26)<>Exercice),"hors exercice","")))))
A27: 46056 | B27: CA | C27: TICKET-02 | D27: 530 | E27: =IF($D27="","",IFERROR(VLOOKUP($D27,'Plan comptable'!$H:$I,2,FALSE),"compte hors plan")) | F27: Vente au comptant · EXEMPLE | G27: MAG1 | H27: 23800 | J27: =IF($D27="","",IF(AND($H27<>"",$I27<>""),"débit ET crédit",IF(AND($H27="",$I27=""),"montant manquant",IF(ISNA(MATCH($D27,'Plan comptable'!$H:$H,0)),"compte hors plan",IF(AND($A27<>"",YEAR($A27)<>Exercice),"hors exercice","")))))
A28: 46056 | B28: CA | C28: TICKET-02 | D28: 700 | E28: =IF($D28="","",IFERROR(VLOOKUP($D28,'Plan comptable'!$H:$I,2,FALSE),"compte hors plan")) | F28: Vente de marchandises · EXEMPLE | G28: MAG1 | I28: 20000 | J28: =IF($D28="","",IF(AND($H28<>"",$I28<>""),"débit ET crédit",IF(AND($H28="",$I28=""),"montant manquant",IF(ISNA(MATCH($D28,'Plan comptable'!$H:$H,0)),"compte hors plan",IF(AND($A28<>"",YEAR($A28)<>Exercice),"hors exercice","")))))
A29: 46056 | B29: CA | C29: TICKET-02 | D29: 4457 | E29: =IF($D29="","",IFERROR(VLOOKUP($D29,'Plan comptable'!$H:$I,2,FALSE),"compte hors plan")) | F29: TVA collectée 19 % · EXEMPLE | G29: MAG1 | I29: 3800 | J29: =IF($D29="","",IF(AND($H29<>"",$I29<>""),"débit ET crédit",IF(AND($H29="",$I29=""),"montant manquant",IF(ISNA(MATCH($D29,'Plan comptable'!$H:$H,0)),"compte hors plan",IF(AND($A29<>"",YEAR($A29)<>Exercice),"hors exercice","")))))
A30: 46081 | B30: OD | C30: AMORT-02 | D30: 681 | E30: =IF($D30="","",IFERROR(VLOOKUP($D30,'Plan comptable'!$H:$I,2,FALSE),"compte hors plan")) | F30: Dotation aux amortissements · EXEMPLE | H30: 1600 | J30: =IF($D30="","",IF(AND($H30<>"",$I30<>""),"débit ET crédit",IF(AND($H30="",$I30=""),"montant manquant",IF(ISNA(MATCH($D30,'Plan comptable'!$H:$H,0)),"compte hors plan",IF(AND($A30<>"",YEAR($A30)<>Exercice),"hors exercice","")))))
A31: 46081 | B31: OD | C31: AMORT-02 | D31: 281 | E31: =IF($D31="","",IFERROR(VLOOKUP($D31,'Plan comptable'!$H:$I,2,FALSE),"compte hors plan")) | F31: Amortissement du matériel · EXEMPLE | I31: 1600 | J31: =IF($D31="","",IF(AND($H31<>"",$I31<>""),"débit ET crédit",IF(AND($H31="",$I31=""),"montant manquant",IF(ISNA(MATCH($D31,'Plan comptable'!$H:$H,0)),"compte hors plan",IF(AND($A31<>"",YEAR($A31)<>Exercice),"hors exercice","")))))
A32: 46112 | B32: OD | C32: TVA-03 | D32: 4457 | E32: =IF($D32="","",IFERROR(VLOOKUP($D32,'Plan comptable'!$H:$I,2,FALSE),"compte hors plan")) | F32: TVA collectée du trimestre · EXEMPLE | H32: 22800 | J32: =IF($D32="","",IF(AND($H32<>"",$I32<>""),"débit ET crédit",IF(AND($H32="",$I32=""),"montant manquant",IF(ISNA(MATCH($D32,'Plan comptable'!$H:$H,0)),"compte hors plan",IF(AND($A32<>"",YEAR($A32)<>Exercice),"hors exercice","")))))
A33: 46112 | B33: OD | C33: TVA-03 | D33: 44566 | E33: =IF($D33="","",IFERROR(VLOOKUP($D33,'Plan comptable'!$H:$I,2,FALSE),"compte hors plan")) | F33: TVA déductible du trimestre · EXEMPLE | I33: 11400 | J33: =IF($D33="","",IF(AND($H33<>"",$I33<>""),"débit ET crédit",IF(AND($H33="",$I33=""),"montant manquant",IF(ISNA(MATCH($D33,'Plan comptable'!$H:$H,0)),"compte hors plan",IF(AND($A33<>"",YEAR($A33)<>Exercice),"hors exercice","")))))
A34: 46112 | B34: OD | C34: TVA-03 | D34: 4459 | E34: =IF($D34="","",IFERROR(VLOOKUP($D34,'Plan comptable'!$H:$I,2,FALSE),"compte hors plan")) | F34: TVA à décaisser · EXEMPLE | I34: 11400 | J34: =IF($D34="","",IF(AND($H34<>"",$I34<>""),"débit ET crédit",IF(AND($H34="",$I34=""),"montant manquant",IF(ISNA(MATCH($D34,'Plan comptable'!$H:$H,0)),"compte hors plan",IF(AND($A34<>"",YEAR($A34)<>Exercice),"hors exercice","")))))
E35: =IF($D35="","",IFERROR(VLOOKUP($D35,'Plan comptable'!$H:$I,2,FALSE),"compte hors plan")) | J35: =IF($D35="","",IF(AND($H35<>"",$I35<>""),"débit ET crédit",IF(AND($H35="",$I35=""),"montant manquant",IF(ISNA(MATCH($D35,'Plan comptable'!$H:$H,0)),"compte hors plan",IF(AND($A35<>"",YEAR($A35)<>Exercice),"hors exercice","")))))
E36: =IF($D36="","",IFERROR(VLOOKUP($D36,'Plan comptable'!$H:$I,2,FALSE),"compte hors plan")) | J36: =IF($D36="","",IF(AND($H36<>"",$I36<>""),"débit ET crédit",IF(AND($H36="",$I36=""),"montant manquant",IF(ISNA(MATCH($D36,'Plan comptable'!$H:$H,0)),"compte hors plan",IF(AND($A36<>"",YEAR($A36)<>Exercice),"hors exercice","")))))
E37: =IF($D37="","",IFERROR(VLOOKUP($D37,'Plan comptable'!$H:$I,2,FALSE),"compte hors plan")) | J37: =IF($D37="","",IF(AND($H37<>"",$I37<>""),"débit ET crédit",IF(AND($H37="",$I37=""),"montant manquant",IF(ISNA(MATCH($D37,'Plan comptable'!$H:$H,0)),"compte hors plan",IF(AND($A37<>"",YEAR($A37)<>Exercice),"hors exercice","")))))
E38: =IF($D38="","",IFERROR(VLOOKUP($D38,'Plan comptable'!$H:$I,2,FALSE),"compte hors plan")) | J38: =IF($D38="","",IF(AND($H38<>"",$I38<>""),"débit ET crédit",IF(AND($H38="",$I38=""),"montant manquant",IF(ISNA(MATCH($D38,'Plan comptable'!$H:$H,0)),"compte hors plan",IF(AND($A38<>"",YEAR($A38)<>Exercice),"hors exercice","")))))
E39: =IF($D39="","",IFERROR(VLOOKUP($D39,'Plan comptable'!$H:$I,2,FALSE),"compte hors plan")) | J39: =IF($D39="","",IF(AND($H39<>"",$I39<>""),"débit ET crédit",IF(AND($H39="",$I39=""),"montant manquant",IF(ISNA(MATCH($D39,'Plan comptable'!$H:$H,0)),"compte hors plan",IF(AND($A39<>"",YEAR($A39)<>Exercice),"hors exercice","")))))
E40: =IF($D40="","",IFERROR(VLOOKUP($D40,'Plan comptable'!$H:$I,2,FALSE),"compte hors plan")) | J40: =IF($D40="","",IF(AND($H40<>"",$I40<>""),"débit ET crédit",IF(AND($H40="",$I40=""),"montant manquant",IF(ISNA(MATCH($D40,'Plan comptable'!$H:$H,0)),"compte hors plan",IF(AND($A40<>"",YEAR($A40)<>Exercice),"hors exercice","")))))
E41: =IF($D41="","",IFERROR(VLOOKUP($D41,'Plan comptable'!$H:$I,2,FALSE),"compte hors plan")) | J41: =IF($D41="","",IF(AND($H41<>"",$I41<>""),"débit ET crédit",IF(AND($H41="",$I41=""),"montant manquant",IF(ISNA(MATCH($D41,'Plan comptable'!$H:$H,0)),"compte hors plan",IF(AND($A41<>"",YEAR($A41)<>Exercice),"hors exercice","")))))
E42: =IF($D42="","",IFERROR(VLOOKUP($D42,'Plan comptable'!$H:$I,2,FALSE),"compte hors plan")) | J42: =IF($D42="","",IF(AND($H42<>"",$I42<>""),"débit ET crédit",IF(AND($H42="",$I42=""),"montant manquant",IF(ISNA(MATCH($D42,'Plan comptable'!$H:$H,0)),"compte hors plan",IF(AND($A42<>"",YEAR($A42)<>Exercice),"hors exercice","")))))
E43: =IF($D43="","",IFERROR(VLOOKUP($D43,'Plan comptable'!$H:$I,2,FALSE),"compte hors plan")) | J43: =IF($D43="","",IF(AND($H43<>"",$I43<>""),"débit ET crédit",IF(AND($H43="",$I43=""),"montant manquant",IF(ISNA(MATCH($D43,'Plan comptable'!$H:$H,0)),"compte hors plan",IF(AND($A43<>"",YEAR($A43)<>Exercice),"hors exercice","")))))
E44: =IF($D44="","",IFERROR(VLOOKUP($D44,'Plan comptable'!$H:$I,2,FALSE),"compte hors plan")) | J44: =IF($D44="","",IF(AND($H44<>"",$I44<>""),"débit ET crédit",IF(AND($H44="",$I44=""),"montant manquant",IF(ISNA(MATCH($D44,'Plan comptable'!$H:$H,0)),"compte hors plan",IF(AND($A44<>"",YEAR($A44)<>Exercice),"hors exercice","")))))
E45: =IF($D45="","",IFERROR(VLOOKUP($D45,'Plan comptable'!$H:$I,2,FALSE),"compte hors plan")) | J45: =IF($D45="","",IF(AND($H45<>"",$I45<>""),"débit ET crédit",IF(AND($H45="",$I45=""),"montant manquant",IF(ISNA(MATCH($D45,'Plan comptable'!$H:$H,0)),"compte hors plan",IF(AND($A45<>"",YEAR($A45)<>Exercice),"hors exercice","")))))
E46: =IF($D46="","",IFERROR(VLOOKUP($D46,'Plan comptable'!$H:$I,2,FALSE),"compte hors plan")) | J46: =IF($D46="","",IF(AND($H46<>"",$I46<>""),"débit ET crédit",IF(AND($H46="",$I46=""),"montant manquant",IF(ISNA(MATCH($D46,'Plan comptable'!$H:$H,0)),"compte hors plan",IF(AND($A46<>"",YEAR($A46)<>Exercice),"hors exercice","")))))
... E2007: =IF($D2007="","",IFERROR(VLOOKUP($D2007,'Plan comptable'!$H:$I,2,FALSE),"compte hors plan")) | J2007: =IF($D2007="","",IF(AND($H2007<>"",$I2007<>""),"débit ET crédit",IF(AND($H2007="",$I2007=""),"montant manquant",IF(ISNA(MATCH($D2007,'Plan comptable'!$H:$H,0)),"compte hors plan",IF(AND($A2007<>"",YEAR($A2007)<>Exercice),"hors exercice","")))))

Sheet Grand livre
A1: GRAND LIVRE
A2: الأستاذ العام
A3: =Societe&" · Exercice "&Exercice
A5: Compte : | C5: 411 | D5: =IFERROR(VLOOKUP($C$5,'Plan comptable'!$H:$I,2,FALSE),"—") | H5: choisissez un compte en C5
D6: Totaux du compte | E6: =SUMIF('Journal'!$D$8:$D$2007,$C$5,'Journal'!$H$8:$H$2007) | F6: =SUMIF('Journal'!$D$8:$D$2007,$C$5,'Journal'!$I$8:$I$2007) | G6: =$E$6-$F$6
A7: Date | B7: Journal | C7: N° pièce | D7: Libellé | E7: Débit | F7: Crédit | G7: Solde cumulé | H7: réf. (technique)
A8: =IF($H8="","",INDEX('Journal'!$A$8:$A$2007,$H8)) | B8: =IF($H8="","",INDEX('Journal'!$B$8:$B$2007,$H8)) | C8: =IF($H8="","",INDEX('Journal'!$C$8:$C$2007,$H8)) | D8: =IF($H8="","",INDEX('Journal'!$F$8:$F$2007,$H8)) | E8: =IF($H8="","",INDEX('Journal'!$H$8:$H$2007,$H8)) | F8: =IF($H8="","",INDEX('Journal'!$I$8:$I$2007,$H8)) | G8: =IF($H8="","",N(G7)+N(E8)-N(F8)) | H8: {=IFERROR(SMALL(IF('Journal'!$D$8:$D$2007=$C$5,ROW('Journal'!$D$8:$D$2007)-7),1),"")}
A9: =IF($H9="","",INDEX('Journal'!$A$8:$A$2007,$H9)) | B9: =IF($H9="","",INDEX('Journal'!$B$8:$B$2007,$H9)) | C9: =IF($H9="","",INDEX('Journal'!$C$8:$C$2007,$H9)) | D9: =IF($H9="","",INDEX('Journal'!$F$8:$F$2007,$H9)) | E9: =IF($H9="","",INDEX('Journal'!$H$8:$H$2007,$H9)) | F9: =IF($H9="","",INDEX('Journal'!$I$8:$I$2007,$H9)) | G9: =IF($H9="","",N(G8)+N(E9)-N(F9)) | H9: {=IFERROR(SMALL(IF('Journal'!$D$8:$D$2007=$C$5,ROW('Journal'!$D$8:$D$2007)-7),2),"")}
A10: =IF($H10="","",INDEX('Journal'!$A$8:$A$2007,$H10)) | B10: =IF($H10="","",INDEX('Journal'!$B$8:$B$2007,$H10)) | C10: =IF($H10="","",INDEX('Journal'!$C$8:$C$2007,$H10)) | D10: =IF($H10="","",INDEX('Journal'!$F$8:$F$2007,$H10)) | E10: =IF($H10="","",INDEX('Journal'!$H$8:$H$2007,$H10)) | F10: =IF($H10="","",INDEX('Journal'!$I$8:$I$2007,$H10)) | G10: =IF($H10="","",N(G9)+N(E10)-N(F10)) | H10: {=IFERROR(SMALL(IF('Journal'!$D$8:$D$2007=$C$5,ROW('Journal'!$D$8:$D$2007)-7),3),"")}
A11: =IF($H11="","",INDEX('Journal'!$A$8:$A$2007,$H11)) | B11: =IF($H11="","",INDEX('Journal'!$B$8:$B$2007,$H11)) | C11: =IF($H11="","",INDEX('Journal'!$C$8:$C$2007,$H11)) | D11: =IF($H11="","",INDEX('Journal'!$F$8:$F$2007,$H11)) | E11: =IF($H11="","",INDEX('Journal'!$H$8:$H$2007,$H11)) | F11: =IF($H11="","",INDEX('Journal'!$I$8:$I$2007,$H11)) | G11: =IF($H11="","",N(G10)+N(E11)-N(F11)) | H11: {=IFERROR(SMALL(IF('Journal'!$D$8:$D$2007=$C$5,ROW('Journal'!$D$8:$D$2007)-7),4),"")}
A12: =IF($H12="","",INDEX('Journal'!$A$8:$A$2007,$H12)) | B12: =IF($H12="","",INDEX('Journal'!$B$8:$B$2007,$H12)) | C12: =IF($H12="","",INDEX('Journal'!$C$8:$C$2007,$H12)) | D12: =IF($H12="","",INDEX('Journal'!$F$8:$F$2007,$H12)) | E12: =IF($H12="","",INDEX('Journal'!$H$8:$H$2007,$H12)) | F12: =IF($H12="","",INDEX('Journal'!$I$8:$I$2007,$H12)) | G12: =IF($H12="","",N(G11)+N(E12)-N(F12)) | H12: {=IFERROR(SMALL(IF('Journal'!$D$8:$D$2007=$C$5,ROW('Journal'!$D$8:$D$2007)-7),5),"")}
A13: =IF($H13="","",INDEX('Journal'!$A$8:$A$2007,$H13)) | B13: =IF($H13="","",INDEX('Journal'!$B$8:$B$2007,$H13)) | C13: =IF($H13="","",INDEX('Journal'!$C$8:$C$2007,$H13)) | D13: =IF($H13="","",INDEX('Journal'!$F$8:$F$2007,$H13)) | E13: =IF($H13="","",INDEX('Journal'!$H$8:$H$2007,$H13)) | F13: =IF($H13="","",INDEX('Journal'!$I$8:$I$2007,$H13)) | G13: =IF($H13="","",N(G12)+N(E13)-N(F13)) | H13: {=IFERROR(SMALL(IF('Journal'!$D$8:$D$2007=$C$5,ROW('Journal'!$D$8:$D$2007)-7),6),"")}
A14: =IF($H14="","",INDEX('Journal'!$A$8:$A$2007,$H14)) | B14: =IF($H14="","",INDEX('Journal'!$B$8:$B$2007,$H14)) | C14: =IF($H14="","",INDEX('Journal'!$C$8:$C$2007,$H14)) | D14: =IF($H14="","",INDEX('Journal'!$F$8:$F$2007,$H14)) | E14: =IF($H14="","",INDEX('Journal'!$H$8:$H$2007,$H14)) | F14: =IF($H14="","",INDEX('Journal'!$I$8:$I$2007,$H14)) | G14: =IF($H14="","",N(G13)+N(E14)-N(F14)) | H14: {=IFERROR(SMALL(IF('Journal'!$D$8:$D$2007=$C$5,ROW('Journal'!$D$8:$D$2007)-7),7),"")}
A15: =IF($H15="","",INDEX('Journal'!$A$8:$A$2007,$H15)) | B15: =IF($H15="","",INDEX('Journal'!$B$8:$B$2007,$H15)) | C15: =IF($H15="","",INDEX('Journal'!$C$8:$C$2007,$H15)) | D15: =IF($H15="","",INDEX('Journal'!$F$8:$F$2007,$H15)) | E15: =IF($H15="","",INDEX('Journal'!$H$8:$H$2007,$H15)) | F15: =IF($H15="","",INDEX('Journal'!$I$8:$I$2007,$H15)) | G15: =IF($H15="","",N(G14)+N(E15)-N(F15)) | H15: {=IFERROR(SMALL(IF('Journal'!$D$8:$D$2007=$C$5,ROW('Journal'!$D$8:$D$2007)-7),8),"")}
A16: =IF($H16="","",INDEX('Journal'!$A$8:$A$2007,$H16)) | B16: =IF($H16="","",INDEX('Journal'!$B$8:$B$2007,$H16)) | C16: =IF($H16="","",INDEX('Journal'!$C$8:$C$2007,$H16)) | D16: =IF($H16="","",INDEX('Journal'!$F$8:$F$2007,$H16)) | E16: =IF($H16="","",INDEX('Journal'!$H$8:$H$2007,$H16)) | F16: =IF($H16="","",INDEX('Journal'!$I$8:$I$2007,$H16)) | G16: =IF($H16="","",N(G15)+N(E16)-N(F16)) | H16: {=IFERROR(SMALL(IF('Journal'!$D$8:$D$2007=$C$5,ROW('Journal'!$D$8:$D$2007)-7),9),"")}
A17: =IF($H17="","",INDEX('Journal'!$A$8:$A$2007,$H17)) | B17: =IF($H17="","",INDEX('Journal'!$B$8:$B$2007,$H17)) | C17: =IF($H17="","",INDEX('Journal'!$C$8:$C$2007,$H17)) | D17: =IF($H17="","",INDEX('Journal'!$F$8:$F$2007,$H17)) | E17: =IF($H17="","",INDEX('Journal'!$H$8:$H$2007,$H17)) | F17: =IF($H17="","",INDEX('Journal'!$I$8:$I$2007,$H17)) | G17: =IF($H17="","",N(G16)+N(E17)-N(F17)) | H17: {=IFERROR(SMALL(IF('Journal'!$D$8:$D$2007=$C$5,ROW('Journal'!$D$8:$D$2007)-7),10),"")}
A18: =IF($H18="","",INDEX('Journal'!$A$8:$A$2007,$H18)) | B18: =IF($H18="","",INDEX('Journal'!$B$8:$B$2007,$H18)) | C18: =IF($H18="","",INDEX('Journal'!$C$8:$C$2007,$H18)) | D18: =IF($H18="","",INDEX('Journal'!$F$8:$F$2007,$H18)) | E18: =IF($H18="","",INDEX('Journal'!$H$8:$H$2007,$H18)) | F18: =IF($H18="","",INDEX('Journal'!$I$8:$I$2007,$H18)) | G18: =IF($H18="","",N(G17)+N(E18)-N(F18)) | H18: {=IFERROR(SMALL(IF('Journal'!$D$8:$D$2007=$C$5,ROW('Journal'!$D$8:$D$2007)-7),11),"")}
A19: =IF($H19="","",INDEX('Journal'!$A$8:$A$2007,$H19)) | B19: =IF($H19="","",INDEX('Journal'!$B$8:$B$2007,$H19)) | C19: =IF($H19="","",INDEX('Journal'!$C$8:$C$2007,$H19)) | D19: =IF($H19="","",INDEX('Journal'!$F$8:$F$2007,$H19)) | E19: =IF($H19="","",INDEX('Journal'!$H$8:$H$2007,$H19)) | F19: =IF($H19="","",INDEX('Journal'!$I$8:$I$2007,$H19)) | G19: =IF($H19="","",N(G18)+N(E19)-N(F19)) | H19: {=IFERROR(SMALL(IF('Journal'!$D$8:$D$2007=$C$5,ROW('Journal'!$D$8:$D$2007)-7),12),"")}
A20: =IF($H20="","",INDEX('Journal'!$A$8:$A$2007,$H20)) | B20: =IF($H20="","",INDEX('Journal'!$B$8:$B$2007,$H20)) | C20: =IF($H20="","",INDEX('Journal'!$C$8:$C$2007,$H20)) | D20: =IF($H20="","",INDEX('Journal'!$F$8:$F$2007,$H20)) | E20: =IF($H20="","",INDEX('Journal'!$H$8:$H$2007,$H20)) | F20: =IF($H20="","",INDEX('Journal'!$I$8:$I$2007,$H20)) | G20: =IF($H20="","",N(G19)+N(E20)-N(F20)) | H20: {=IFERROR(SMALL(IF('Journal'!$D$8:$D$2007=$C$5,ROW('Journal'!$D$8:$D$2007)-7),13),"")}
A21: =IF($H21="","",INDEX('Journal'!$A$8:$A$2007,$H21)) | B21: =IF($H21="","",INDEX('Journal'!$B$8:$B$2007,$H21)) | C21: =IF($H21="","",INDEX('Journal'!$C$8:$C$2007,$H21)) | D21: =IF($H21="","",INDEX('Journal'!$F$8:$F$2007,$H21)) | E21: =IF($H21="","",INDEX('Journal'!$H$8:$H$2007,$H21)) | F21: =IF($H21="","",INDEX('Journal'!$I$8:$I$2007,$H21)) | G21: =IF($H21="","",N(G20)+N(E21)-N(F21)) | H21: {=IFERROR(SMALL(IF('Journal'!$D$8:$D$2007=$C$5,ROW('Journal'!$D$8:$D$2007)-7),14),"")}
A22: =IF($H22="","",INDEX('Journal'!$A$8:$A$2007,$H22)) | B22: =IF($H22="","",INDEX('Journal'!$B$8:$B$2007,$H22)) | C22: =IF($H22="","",INDEX('Journal'!$C$8:$C$2007,$H22)) | D22: =IF($H22="","",INDEX('Journal'!$F$8:$F$2007,$H22)) | E22: =IF($H22="","",INDEX('Journal'!$H$8:$H$2007,$H22)) | F22: =IF($H22="","",INDEX('Journal'!$I$8:$I$2007,$H22)) | G22: =IF($H22="","",N(G21)+N(E22)-N(F22)) | H22: {=IFERROR(SMALL(IF('Journal'!$D$8:$D$2007=$C$5,ROW('Journal'!$D$8:$D$2007)-7),15),"")}
A23: =IF($H23="","",INDEX('Journal'!$A$8:$A$2007,$H23)) | B23: =IF($H23="","",INDEX('Journal'!$B$8:$B$2007,$H23)) | C23: =IF($H23="","",INDEX('Journal'!$C$8:$C$2007,$H23)) | D23: =IF($H23="","",INDEX('Journal'!$F$8:$F$2007,$H23)) | E23: =IF($H23="","",INDEX('Journal'!$H$8:$H$2007,$H23)) | F23: =IF($H23="","",INDEX('Journal'!$I$8:$I$2007,$H23)) | G23: =IF($H23="","",N(G22)+N(E23)-N(F23)) | H23: {=IFERROR(SMALL(IF('Journal'!$D$8:$D$2007=$C$5,ROW('Journal'!$D$8:$D$2007)-7),16),"")}
A24: =IF($H24="","",INDEX('Journal'!$A$8:$A$2007,$H24)) | B24: =IF($H24="","",INDEX('Journal'!$B$8:$B$2007,$H24)) | C24: =IF($H24="","",INDEX('Journal'!$C$8:$C$2007,$H24)) | D24: =IF($H24="","",INDEX('Journal'!$F$8:$F$2007,$H24)) | E24: =IF($H24="","",INDEX('Journal'!$H$8:$H$2007,$H24)) | F24: =IF($H24="","",INDEX('Journal'!$I$8:$I$2007,$H24)) | G24: =IF($H24="","",N(G23)+N(E24)-N(F24)) | H24: {=IFERROR(SMALL(IF('Journal'!$D$8:$D$2007=$C$5,ROW('Journal'!$D$8:$D$2007)-7),17),"")}
A25: =IF($H25="","",INDEX('Journal'!$A$8:$A$2007,$H25)) | B25: =IF($H25="","",INDEX('Journal'!$B$8:$B$2007,$H25)) | C25: =IF($H25="","",INDEX('Journal'!$C$8:$C$2007,$H25)) | D25: =IF($H25="","",INDEX('Journal'!$F$8:$F$2007,$H25)) | E25: =IF($H25="","",INDEX('Journal'!$H$8:$H$2007,$H25)) | F25: =IF($H25="","",INDEX('Journal'!$I$8:$I$2007,$H25)) | G25: =IF($H25="","",N(G24)+N(E25)-N(F25)) | H25: {=IFERROR(SMALL(IF('Journal'!$D$8:$D$2007=$C$5,ROW('Journal'!$D$8:$D$2007)-7),18),"")}
A26: =IF($H26="","",INDEX('Journal'!$A$8:$A$2007,$H26)) | B26: =IF($H26="","",INDEX('Journal'!$B$8:$B$2007,$H26)) | C26: =IF($H26="","",INDEX('Journal'!$C$8:$C$2007,$H26)) | D26: =IF($H26="","",INDEX('Journal'!$F$8:$F$2007,$H26)) | E26: =IF($H26="","",INDEX('Journal'!$H$8:$H$2007,$H26)) | F26: =IF($H26="","",INDEX('Journal'!$I$8:$I$2007,$H26)) | G26: =IF($H26="","",N(G25)+N(E26)-N(F26)) | H26: {=IFERROR(SMALL(IF('Journal'!$D$8:$D$2007=$C$5,ROW('Journal'!$D$8:$D$2007)-7),19),"")}
A27: =IF($H27="","",INDEX('Journal'!$A$8:$A$2007,$H27)) | B27: =IF($H27="","",INDEX('Journal'!$B$8:$B$2007,$H27)) | C27: =IF($H27="","",INDEX('Journal'!$C$8:$C$2007,$H27)) | D27: =IF($H27="","",INDEX('Journal'!$F$8:$F$2007,$H27)) | E27: =IF($H27="","",INDEX('Journal'!$H$8:$H$2007,$H27)) | F27: =IF($H27="","",INDEX('Journal'!$I$8:$I$2007,$H27)) | G27: =IF($H27="","",N(G26)+N(E27)-N(F27)) | H27: {=IFERROR(SMALL(IF('Journal'!$D$8:$D$2007=$C$5,ROW('Journal'!$D$8:$D$2007)-7),20),"")}
A28: =IF($H28="","",INDEX('Journal'!$A$8:$A$2007,$H28)) | B28: =IF($H28="","",INDEX('Journal'!$B$8:$B$2007,$H28)) | C28: =IF($H28="","",INDEX('Journal'!$C$8:$C$2007,$H28)) | D28: =IF($H28="","",INDEX('Journal'!$F$8:$F$2007,$H28)) | E28: =IF($H28="","",INDEX('Journal'!$H$8:$H$2007,$H28)) | F28: =IF($H28="","",INDEX('Journal'!$I$8:$I$2007,$H28)) | G28: =IF($H28="","",N(G27)+N(E28)-N(F28)) | H28: {=IFERROR(SMALL(IF('Journal'!$D$8:$D$2007=$C$5,ROW('Journal'!$D$8:$D$2007)-7),21),"")}
A29: =IF($H29="","",INDEX('Journal'!$A$8:$A$2007,$H29)) | B29: =IF($H29="","",INDEX('Journal'!$B$8:$B$2007,$H29)) | C29: =IF($H29="","",INDEX('Journal'!$C$8:$C$2007,$H29)) | D29: =IF($H29="","",INDEX('Journal'!$F$8:$F$2007,$H29)) | E29: =IF($H29="","",INDEX('Journal'!$H$8:$H$2007,$H29)) | F29: =IF($H29="","",INDEX('Journal'!$I$8:$I$2007,$H29)) | G29: =IF($H29="","",N(G28)+N(E29)-N(F29)) | H29: {=IFERROR(SMALL(IF('Journal'!$D$8:$D$2007=$C$5,ROW('Journal'!$D$8:$D$2007)-7),22),"")}
A30: =IF($H30="","",INDEX('Journal'!$A$8:$A$2007,$H30)) | B30: =IF($H30="","",INDEX('Journal'!$B$8:$B$2007,$H30)) | C30: =IF($H30="","",INDEX('Journal'!$C$8:$C$2007,$H30)) | D30: =IF($H30="","",INDEX('Journal'!$F$8:$F$2007,$H30)) | E30: =IF($H30="","",INDEX('Journal'!$H$8:$H$2007,$H30)) | F30: =IF($H30="","",INDEX('Journal'!$I$8:$I$2007,$H30)) | G30: =IF($H30="","",N(G29)+N(E30)-N(F30)) | H30: {=IFERROR(SMALL(IF('Journal'!$D$8:$D$2007=$C$5,ROW('Journal'!$D$8:$D$2007)-7),23),"")}
A31: =IF($H31="","",INDEX('Journal'!$A$8:$A$2007,$H31)) | B31: =IF($H31="","",INDEX('Journal'!$B$8:$B$2007,$H31)) | C31: =IF($H31="","",INDEX('Journal'!$C$8:$C$2007,$H31)) | D31: =IF($H31="","",INDEX('Journal'!$F$8:$F$2007,$H31)) | E31: =IF($H31="","",INDEX('Journal'!$H$8:$H$2007,$H31)) | F31: =IF($H31="","",INDEX('Journal'!$I$8:$I$2007,$H31)) | G31: =IF($H31="","",N(G30)+N(E31)-N(F31)) | H31: {=IFERROR(SMALL(IF('Journal'!$D$8:$D$2007=$C$5,ROW('Journal'!$D$8:$D$2007)-7),24),"")}
A32: =IF($H32="","",INDEX('Journal'!$A$8:$A$2007,$H32)) | B32: =IF($H32="","",INDEX('Journal'!$B$8:$B$2007,$H32)) | C32: =IF($H32="","",INDEX('Journal'!$C$8:$C$2007,$H32)) | D32: =IF($H32="","",INDEX('Journal'!$F$8:$F$2007,$H32)) | E32: =IF($H32="","",INDEX('Journal'!$H$8:$H$2007,$H32)) | F32: =IF($H32="","",INDEX('Journal'!$I$8:$I$2007,$H32)) | G32: =IF($H32="","",N(G31)+N(E32)-N(F32)) | H32: {=IFERROR(SMALL(IF('Journal'!$D$8:$D$2007=$C$5,ROW('Journal'!$D$8:$D$2007)-7),25),"")}
A33: =IF($H33="","",INDEX('Journal'!$A$8:$A$2007,$H33)) | B33: =IF($H33="","",INDEX('Journal'!$B$8:$B$2007,$H33)) | C33: =IF($H33="","",INDEX('Journal'!$C$8:$C$2007,$H33)) | D33: =IF($H33="","",INDEX('Journal'!$F$8:$F$2007,$H33)) | E33: =IF($H33="","",INDEX('Journal'!$H$8:$H$2007,$H33)) | F33: =IF($H33="","",INDEX('Journal'!$I$8:$I$2007,$H33)) | G33: =IF($H33="","",N(G32)+N(E33)-N(F33)) | H33: {=IFERROR(SMALL(IF('Journal'!$D$8:$D$2007=$C$5,ROW('Journal'!$D$8:$D$2007)-7),26),"")}
A34: =IF($H34="","",INDEX('Journal'!$A$8:$A$2007,$H34)) | B34: =IF($H34="","",INDEX('Journal'!$B$8:$B$2007,$H34)) | C34: =IF($H34="","",INDEX('Journal'!$C$8:$C$2007,$H34)) | D34: =IF($H34="","",INDEX('Journal'!$F$8:$F$2007,$H34)) | E34: =IF($H34="","",INDEX('Journal'!$H$8:$H$2007,$H34)) | F34: =IF($H34="","",INDEX('Journal'!$I$8:$I$2007,$H34)) | G34: =IF($H34="","",N(G33)+N(E34)-N(F34)) | H34: {=IFERROR(SMALL(IF('Journal'!$D$8:$D$2007=$C$5,ROW('Journal'!$D$8:$D$2007)-7),27),"")}
A35: =IF($H35="","",INDEX('Journal'!$A$8:$A$2007,$H35)) | B35: =IF($H35="","",INDEX('Journal'!$B$8:$B$2007,$H35)) | C35: =IF($H35="","",INDEX('Journal'!$C$8:$C$2007,$H35)) | D35: =IF($H35="","",INDEX('Journal'!$F$8:$F$2007,$H35)) | E35: =IF($H35="","",INDEX('Journal'!$H$8:$H$2007,$H35)) | F35: =IF($H35="","",INDEX('Journal'!$I$8:$I$2007,$H35)) | G35: =IF($H35="","",N(G34)+N(E35)-N(F35)) | H35: {=IFERROR(SMALL(IF('Journal'!$D$8:$D$2007=$C$5,ROW('Journal'!$D$8:$D$2007)-7),28),"")}
A36: =IF($H36="","",INDEX('Journal'!$A$8:$A$2007,$H36)) | B36: =IF($H36="","",INDEX('Journal'!$B$8:$B$2007,$H36)) | C36: =IF($H36="","",INDEX('Journal'!$C$8:$C$2007,$H36)) | D36: =IF($H36="","",INDEX('Journal'!$F$8:$F$2007,$H36)) | E36: =IF($H36="","",INDEX('Journal'!$H$8:$H$2007,$H36)) | F36: =IF($H36="","",INDEX('Journal'!$I$8:$I$2007,$H36)) | G36: =IF($H36="","",N(G35)+N(E36)-N(F36)) | H36: {=IFERROR(SMALL(IF('Journal'!$D$8:$D$2007=$C$5,ROW('Journal'!$D$8:$D$2007)-7),29),"")}
A37: =IF($H37="","",INDEX('Journal'!$A$8:$A$2007,$H37)) | B37: =IF($H37="","",INDEX('Journal'!$B$8:$B$2007,$H37)) | C37: =IF($H37="","",INDEX('Journal'!$C$8:$C$2007,$H37)) | D37: =IF($H37="","",INDEX('Journal'!$F$8:$F$2007,$H37)) | E37: =IF($H37="","",INDEX('Journal'!$H$8:$H$2007,$H37)) | F37: =IF($H37="","",INDEX('Journal'!$I$8:$I$2007,$H37)) | G37: =IF($H37="","",N(G36)+N(E37)-N(F37)) | H37: {=IFERROR(SMALL(IF('Journal'!$D$8:$D$2007=$C$5,ROW('Journal'!$D$8:$D$2007)-7),30),"")}
A38: =IF($H38="","",INDEX('Journal'!$A$8:$A$2007,$H38)) | B38: =IF($H38="","",INDEX('Journal'!$B$8:$B$2007,$H38)) | C38: =IF($H38="","",INDEX('Journal'!$C$8:$C$2007,$H38)) | D38: =IF($H38="","",INDEX('Journal'!$F$8:$F$2007,$H38)) | E38: =IF($H38="","",INDEX('Journal'!$H$8:$H$2007,$H38)) | F38: =IF($H38="","",INDEX('Journal'!$I$8:$I$2007,$H38)) | G38: =IF($H38="","",N(G37)+N(E38)-N(F38)) | H38: {=IFERROR(SMALL(IF('Journal'!$D$8:$D$2007=$C$5,ROW('Journal'!$D$8:$D$2007)-7),31),"")}
A39: =IF($H39="","",INDEX('Journal'!$A$8:$A$2007,$H39)) | B39: =IF($H39="","",INDEX('Journal'!$B$8:$B$2007,$H39)) | C39: =IF($H39="","",INDEX('Journal'!$C$8:$C$2007,$H39)) | D39: =IF($H39="","",INDEX('Journal'!$F$8:$F$2007,$H39)) | E39: =IF($H39="","",INDEX('Journal'!$H$8:$H$2007,$H39)) | F39: =IF($H39="","",INDEX('Journal'!$I$8:$I$2007,$H39)) | G39: =IF($H39="","",N(G38)+N(E39)-N(F39)) | H39: {=IFERROR(SMALL(IF('Journal'!$D$8:$D$2007=$C$5,ROW('Journal'!$D$8:$D$2007)-7),32),"")}
A40: =IF($H40="","",INDEX('Journal'!$A$8:$A$2007,$H40)) | B40: =IF($H40="","",INDEX('Journal'!$B$8:$B$2007,$H40)) | C40: =IF($H40="","",INDEX('Journal'!$C$8:$C$2007,$H40)) | D40: =IF($H40="","",INDEX('Journal'!$F$8:$F$2007,$H40)) | E40: =IF($H40="","",INDEX('Journal'!$H$8:$H$2007,$H40)) | F40: =IF($H40="","",INDEX('Journal'!$I$8:$I$2007,$H40)) | G40: =IF($H40="","",N(G39)+N(E40)-N(F40)) | H40: {=IFERROR(SMALL(IF('Journal'!$D$8:$D$2007=$C$5,ROW('Journal'!$D$8:$D$2007)-7),33),"")}
A41: =IF($H41="","",INDEX('Journal'!$A$8:$A$2007,$H41)) | B41: =IF($H41="","",INDEX('Journal'!$B$8:$B$2007,$H41)) | C41: =IF($H41="","",INDEX('Journal'!$C$8:$C$2007,$H41)) | D41: =IF($H41="","",INDEX('Journal'!$F$8:$F$2007,$H41)) | E41: =IF($H41="","",INDEX('Journal'!$H$8:$H$2007,$H41)) | F41: =IF($H41="","",INDEX('Journal'!$I$8:$I$2007,$H41)) | G41: =IF($H41="","",N(G40)+N(E41)-N(F41)) | H41: {=IFERROR(SMALL(IF('Journal'!$D$8:$D$2007=$C$5,ROW('Journal'!$D$8:$D$2007)-7),34),"")}
A42: =IF($H42="","",INDEX('Journal'!$A$8:$A$2007,$H42)) | B42: =IF($H42="","",INDEX('Journal'!$B$8:$B$2007,$H42)) | C42: =IF($H42="","",INDEX('Journal'!$C$8:$C$2007,$H42)) | D42: =IF($H42="","",INDEX('Journal'!$F$8:$F$2007,$H42)) | E42: =IF($H42="","",INDEX('Journal'!$H$8:$H$2007,$H42)) | F42: =IF($H42="","",INDEX('Journal'!$I$8:$I$2007,$H42)) | G42: =IF($H42="","",N(G41)+N(E42)-N(F42)) | H42: {=IFERROR(SMALL(IF('Journal'!$D$8:$D$2007=$C$5,ROW('Journal'!$D$8:$D$2007)-7),35),"")}
A43: =IF($H43="","",INDEX('Journal'!$A$8:$A$2007,$H43)) | B43: =IF($H43="","",INDEX('Journal'!$B$8:$B$2007,$H43)) | C43: =IF($H43="","",INDEX('Journal'!$C$8:$C$2007,$H43)) | D43: =IF($H43="","",INDEX('Journal'!$F$8:$F$2007,$H43)) | E43: =IF($H43="","",INDEX('Journal'!$H$8:$H$2007,$H43)) | F43: =IF($H43="","",INDEX('Journal'!$I$8:$I$2007,$H43)) | G43: =IF($H43="","",N(G42)+N(E43)-N(F43)) | H43: {=IFERROR(SMALL(IF('Journal'!$D$8:$D$2007=$C$5,ROW('Journal'!$D$8:$D$2007)-7),36),"")}
A44: =IF($H44="","",INDEX('Journal'!$A$8:$A$2007,$H44)) | B44: =IF($H44="","",INDEX('Journal'!$B$8:$B$2007,$H44)) | C44: =IF($H44="","",INDEX('Journal'!$C$8:$C$2007,$H44)) | D44: =IF($H44="","",INDEX('Journal'!$F$8:$F$2007,$H44)) | E44: =IF($H44="","",INDEX('Journal'!$H$8:$H$2007,$H44)) | F44: =IF($H44="","",INDEX('Journal'!$I$8:$I$2007,$H44)) | G44: =IF($H44="","",N(G43)+N(E44)-N(F44)) | H44: {=IFERROR(SMALL(IF('Journal'!$D$8:$D$2007=$C$5,ROW('Journal'!$D$8:$D$2007)-7),37),"")}
A45: =IF($H45="","",INDEX('Journal'!$A$8:$A$2007,$H45)) | B45: =IF($H45="","",INDEX('Journal'!$B$8:$B$2007,$H45)) | C45: =IF($H45="","",INDEX('Journal'!$C$8:$C$2007,$H45)) | D45: =IF($H45="","",INDEX('Journal'!$F$8:$F$2007,$H45)) | E45: =IF($H45="","",INDEX('Journal'!$H$8:$H$2007,$H45)) | F45: =IF($H45="","",INDEX('Journal'!$I$8:$I$2007,$H45)) | G45: =IF($H45="","",N(G44)+N(E45)-N(F45)) | H45: {=IFERROR(SMALL(IF('Journal'!$D$8:$D$2007=$C$5,ROW('Journal'!$D$8:$D$2007)-7),38),"")}
A46: =IF($H46="","",INDEX('Journal'!$A$8:$A$2007,$H46)) | B46: =IF($H46="","",INDEX('Journal'!$B$8:$B$2007,$H46)) | C46: =IF($H46="","",INDEX('Journal'!$C$8:$C$2007,$H46)) | D46: =IF($H46="","",INDEX('Journal'!$F$8:$F$2007,$H46)) | E46: =IF($H46="","",INDEX('Journal'!$H$8:$H$2007,$H46)) | F46: =IF($H46="","",INDEX('Journal'!$I$8:$I$2007,$H46)) | G46: =IF($H46="","",N(G45)+N(E46)-N(F46)) | H46: {=IFERROR(SMALL(IF('Journal'!$D$8:$D$2007=$C$5,ROW('Journal'!$D$8:$D$2007)-7),39),"")}
A47: =IF($H47="","",INDEX('Journal'!$A$8:$A$2007,$H47)) | B47: =IF($H47="","",INDEX('Journal'!$B$8:$B$2007,$H47)) | C47: =IF($H47="","",INDEX('Journal'!$C$8:$C$2007,$H47)) | D47: =IF($H47="","",INDEX('Journal'!$F$8:$F$2007,$H47)) | E47: =IF($H47="","",INDEX('Journal'!$H$8:$H$2007,$H47)) | F47: =IF($H47="","",INDEX('Journal'!$I$8:$I$2007,$H47)) | G47: =IF($H47="","",N(G46)+N(E47)-N(F47)) | H47: {=IFERROR(SMALL(IF('Journal'!$D$8:$D$2007=$C$5,ROW('Journal'!$D$8:$D$2007)-7),40),"")}
A48: =IF($H48="","",INDEX('Journal'!$A$8:$A$2007,$H48)) | B48: =IF($H48="","",INDEX('Journal'!$B$8:$B$2007,$H48)) | C48: =IF($H48="","",INDEX('Journal'!$C$8:$C$2007,$H48)) | D48: =IF($H48="","",INDEX('Journal'!$F$8:$F$2007,$H48)) | E48: =IF($H48="","",INDEX('Journal'!$H$8:$H$2007,$H48)) | F48: =IF($H48="","",INDEX('Journal'!$I$8:$I$2007,$H48)) | G48: =IF($H48="","",N(G47)+N(E48)-N(F48)) | H48: {=IFERROR(SMALL(IF('Journal'!$D$8:$D$2007=$C$5,ROW('Journal'!$D$8:$D$2007)-7),41),"")}
A49: =IF($H49="","",INDEX('Journal'!$A$8:$A$2007,$H49)) | B49: =IF($H49="","",INDEX('Journal'!$B$8:$B$2007,$H49)) | C49: =IF($H49="","",INDEX('Journal'!$C$8:$C$2007,$H49)) | D49: =IF($H49="","",INDEX('Journal'!$F$8:$F$2007,$H49)) | E49: =IF($H49="","",INDEX('Journal'!$H$8:$H$2007,$H49)) | F49: =IF($H49="","",INDEX('Journal'!$I$8:$I$2007,$H49)) | G49: =IF($H49="","",N(G48)+N(E49)-N(F49)) | H49: {=IFERROR(SMALL(IF('Journal'!$D$8:$D$2007=$C$5,ROW('Journal'!$D$8:$D$2007)-7),42),"")}
A50: =IF($H50="","",INDEX('Journal'!$A$8:$A$2007,$H50)) | B50: =IF($H50="","",INDEX('Journal'!$B$8:$B$2007,$H50)) | C50: =IF($H50="","",INDEX('Journal'!$C$8:$C$2007,$H50)) | D50: =IF($H50="","",INDEX('Journal'!$F$8:$F$2007,$H50)) | E50: =IF($H50="","",INDEX('Journal'!$H$8:$H$2007,$H50)) | F50: =IF($H50="","",INDEX('Journal'!$I$8:$I$2007,$H50)) | G50: =IF($H50="","",N(G49)+N(E50)-N(F50)) | H50: {=IFERROR(SMALL(IF('Journal'!$D$8:$D$2007=$C$5,ROW('Journal'!$D$8:$D$2007)-7),43),"")}
A51: =IF($H51="","",INDEX('Journal'!$A$8:$A$2007,$H51)) | B51: =IF($H51="","",INDEX('Journal'!$B$8:$B$2007,$H51)) | C51: =IF($H51="","",INDEX('Journal'!$C$8:$C$2007,$H51)) | D51: =IF($H51="","",INDEX('Journal'!$F$8:$F$2007,$H51)) | E51: =IF($H51="","",INDEX('Journal'!$H$8:$H$2007,$H51)) | F51: =IF($H51="","",INDEX('Journal'!$I$8:$I$2007,$H51)) | G51: =IF($H51="","",N(G50)+N(E51)-N(F51)) | H51: {=IFERROR(SMALL(IF('Journal'!$D$8:$D$2007=$C$5,ROW('Journal'!$D$8:$D$2007)-7),44),"")}
A52: =IF($H52="","",INDEX('Journal'!$A$8:$A$2007,$H52)) | B52: =IF($H52="","",INDEX('Journal'!$B$8:$B$2007,$H52)) | C52: =IF($H52="","",INDEX('Journal'!$C$8:$C$2007,$H52)) | D52: =IF($H52="","",INDEX('Journal'!$F$8:$F$2007,$H52)) | E52: =IF($H52="","",INDEX('Journal'!$H$8:$H$2007,$H52)) | F52: =IF($H52="","",INDEX('Journal'!$I$8:$I$2007,$H52)) | G52: =IF($H52="","",N(G51)+N(E52)-N(F52)) | H52: {=IFERROR(SMALL(IF('Journal'!$D$8:$D$2007=$C$5,ROW('Journal'!$D$8:$D$2007)-7),45),"")}
A53: =IF($H53="","",INDEX('Journal'!$A$8:$A$2007,$H53)) | B53: =IF($H53="","",INDEX('Journal'!$B$8:$B$2007,$H53)) | C53: =IF($H53="","",INDEX('Journal'!$C$8:$C$2007,$H53)) | D53: =IF($H53="","",INDEX('Journal'!$F$8:$F$2007,$H53)) | E53: =IF($H53="","",INDEX('Journal'!$H$8:$H$2007,$H53)) | F53: =IF($H53="","",INDEX('Journal'!$I$8:$I$2007,$H53)) | G53: =IF($H53="","",N(G52)+N(E53)-N(F53)) | H53: {=IFERROR(SMALL(IF('Journal'!$D$8:$D$2007=$C$5,ROW('Journal'!$D$8:$D$2007)-7),46),"")}
A54: =IF($H54="","",INDEX('Journal'!$A$8:$A$2007,$H54)) | B54: =IF($H54="","",INDEX('Journal'!$B$8:$B$2007,$H54)) | C54: =IF($H54="","",INDEX('Journal'!$C$8:$C$2007,$H54)) | D54: =IF($H54="","",INDEX('Journal'!$F$8:$F$2007,$H54)) | E54: =IF($H54="","",INDEX('Journal'!$H$8:$H$2007,$H54)) | F54: =IF($H54="","",INDEX('Journal'!$I$8:$I$2007,$H54)) | G54: =IF($H54="","",N(G53)+N(E54)-N(F54)) | H54: {=IFERROR(SMALL(IF('Journal'!$D$8:$D$2007=$C$5,ROW('Journal'!$D$8:$D$2007)-7),47),"")}
A55: =IF($H55="","",INDEX('Journal'!$A$8:$A$2007,$H55)) | B55: =IF($H55="","",INDEX('Journal'!$B$8:$B$2007,$H55)) | C55: =IF($H55="","",INDEX('Journal'!$C$8:$C$2007,$H55)) | D55: =IF($H55="","",INDEX('Journal'!$F$8:$F$2007,$H55)) | E55: =IF($H55="","",INDEX('Journal'!$H$8:$H$2007,$H55)) | F55: =IF($H55="","",INDEX('Journal'!$I$8:$I$2007,$H55)) | G55: =IF($H55="","",N(G54)+N(E55)-N(F55)) | H55: {=IFERROR(SMALL(IF('Journal'!$D$8:$D$2007=$C$5,ROW('Journal'!$D$8:$D$2007)-7),48),"")}
A56: =IF($H56="","",INDEX('Journal'!$A$8:$A$2007,$H56)) | B56: =IF($H56="","",INDEX('Journal'!$B$8:$B$2007,$H56)) | C56: =IF($H56="","",INDEX('Journal'!$C$8:$C$2007,$H56)) | D56: =IF($H56="","",INDEX('Journal'!$F$8:$F$2007,$H56)) | E56: =IF($H56="","",INDEX('Journal'!$H$8:$H$2007,$H56)) | F56: =IF($H56="","",INDEX('Journal'!$I$8:$I$2007,$H56)) | G56: =IF($H56="","",N(G55)+N(E56)-N(F56)) | H56: {=IFERROR(SMALL(IF('Journal'!$D$8:$D$2007=$C$5,ROW('Journal'!$D$8:$D$2007)-7),49),"")}
A57: =IF($H57="","",INDEX('Journal'!$A$8:$A$2007,$H57)) | B57: =IF($H57="","",INDEX('Journal'!$B$8:$B$2007,$H57)) | C57: =IF($H57="","",INDEX('Journal'!$C$8:$C$2007,$H57)) | D57: =IF($H57="","",INDEX('Journal'!$F$8:$F$2007,$H57)) | E57: =IF($H57="","",INDEX('Journal'!$H$8:$H$2007,$H57)) | F57: =IF($H57="","",INDEX('Journal'!$I$8:$I$2007,$H57)) | G57: =IF($H57="","",N(G56)+N(E57)-N(F57)) | H57: {=IFERROR(SMALL(IF('Journal'!$D$8:$D$2007=$C$5,ROW('Journal'!$D$8:$D$2007)-7),50),"")}
A58: =IF($H58="","",INDEX('Journal'!$A$8:$A$2007,$H58)) | B58: =IF($H58="","",INDEX('Journal'!$B$8:$B$2007,$H58)) | C58: =IF($H58="","",INDEX('Journal'!$C$8:$C$2007,$H58)) | D58: =IF($H58="","",INDEX('Journal'!$F$8:$F$2007,$H58)) | E58: =IF($H58="","",INDEX('Journal'!$H$8:$H$2007,$H58)) | F58: =IF($H58="","",INDEX('Journal'!$I$8:$I$2007,$H58)) | G58: =IF($H58="","",N(G57)+N(E58)-N(F58)) | H58: {=IFERROR(SMALL(IF('Journal'!$D$8:$D$2007=$C$5,ROW('Journal'!$D$8:$D$2007)-7),51),"")}
A59: =IF($H59="","",INDEX('Journal'!$A$8:$A$2007,$H59)) | B59: =IF($H59="","",INDEX('Journal'!$B$8:$B$2007,$H59)) | C59: =IF($H59="","",INDEX('Journal'!$C$8:$C$2007,$H59)) | D59: =IF($H59="","",INDEX('Journal'!$F$8:$F$2007,$H59)) | E59: =IF($H59="","",INDEX('Journal'!$H$8:$H$2007,$H59)) | F59: =IF($H59="","",INDEX('Journal'!$I$8:$I$2007,$H59)) | G59: =IF($H59="","",N(G58)+N(E59)-N(F59)) | H59: {=IFERROR(SMALL(IF('Journal'!$D$8:$D$2007=$C$5,ROW('Journal'!$D$8:$D$2007)-7),52),"")}
A60: =IF($H60="","",INDEX('Journal'!$A$8:$A$2007,$H60)) | B60: =IF($H60="","",INDEX('Journal'!$B$8:$B$2007,$H60)) | C60: =IF($H60="","",INDEX('Journal'!$C$8:$C$2007,$H60)) | D60: =IF($H60="","",INDEX('Journal'!$F$8:$F$2007,$H60)) | E60: =IF($H60="","",INDEX('Journal'!$H$8:$H$2007,$H60)) | F60: =IF($H60="","",INDEX('Journal'!$I$8:$I$2007,$H60)) | G60: =IF($H60="","",N(G59)+N(E60)-N(F60)) | H60: {=IFERROR(SMALL(IF('Journal'!$D$8:$D$2007=$C$5,ROW('Journal'!$D$8:$D$2007)-7),53),"")}
A61: =IF($H61="","",INDEX('Journal'!$A$8:$A$2007,$H61)) | B61: =IF($H61="","",INDEX('Journal'!$B$8:$B$2007,$H61)) | C61: =IF($H61="","",INDEX('Journal'!$C$8:$C$2007,$H61)) | D61: =IF($H61="","",INDEX('Journal'!$F$8:$F$2007,$H61)) | E61: =IF($H61="","",INDEX('Journal'!$H$8:$H$2007,$H61)) | F61: =IF($H61="","",INDEX('Journal'!$I$8:$I$2007,$H61)) | G61: =IF($H61="","",N(G60)+N(E61)-N(F61)) | H61: {=IFERROR(SMALL(IF('Journal'!$D$8:$D$2007=$C$5,ROW('Journal'!$D$8:$D$2007)-7),54),"")}
A62: =IF($H62="","",INDEX('Journal'!$A$8:$A$2007,$H62)) | B62: =IF($H62="","",INDEX('Journal'!$B$8:$B$2007,$H62)) | C62: =IF($H62="","",INDEX('Journal'!$C$8:$C$2007,$H62)) | D62: =IF($H62="","",INDEX('Journal'!$F$8:$F$2007,$H62)) | E62: =IF($H62="","",INDEX('Journal'!$H$8:$H$2007,$H62)) | F62: =IF($H62="","",INDEX('Journal'!$I$8:$I$2007,$H62)) | G62: =IF($H62="","",N(G61)+N(E62)-N(F62)) | H62: {=IFERROR(SMALL(IF('Journal'!$D$8:$D$2007=$C$5,ROW('Journal'!$D$8:$D$2007)-7),55),"")}
A63: =IF($H63="","",INDEX('Journal'!$A$8:$A$2007,$H63)) | B63: =IF($H63="","",INDEX('Journal'!$B$8:$B$2007,$H63)) | C63: =IF($H63="","",INDEX('Journal'!$C$8:$C$2007,$H63)) | D63: =IF($H63="","",INDEX('Journal'!$F$8:$F$2007,$H63)) | E63: =IF($H63="","",INDEX('Journal'!$H$8:$H$2007,$H63)) | F63: =IF($H63="","",INDEX('Journal'!$I$8:$I$2007,$H63)) | G63: =IF($H63="","",N(G62)+N(E63)-N(F63)) | H63: {=IFERROR(SMALL(IF('Journal'!$D$8:$D$2007=$C$5,ROW('Journal'!$D$8:$D$2007)-7),56),"")}
A64: =IF($H64="","",INDEX('Journal'!$A$8:$A$2007,$H64)) | B64: =IF($H64="","",INDEX('Journal'!$B$8:$B$2007,$H64)) | C64: =IF($H64="","",INDEX('Journal'!$C$8:$C$2007,$H64)) | D64: =IF($H64="","",INDEX('Journal'!$F$8:$F$2007,$H64)) | E64: =IF($H64="","",INDEX('Journal'!$H$8:$H$2007,$H64)) | F64: =IF($H64="","",INDEX('Journal'!$I$8:$I$2007,$H64)) | G64: =IF($H64="","",N(G63)+N(E64)-N(F64)) | H64: {=IFERROR(SMALL(IF('Journal'!$D$8:$D$2007=$C$5,ROW('Journal'!$D$8:$D$2007)-7),57),"")}
A65: =IF($H65="","",INDEX('Journal'!$A$8:$A$2007,$H65)) | B65: =IF($H65="","",INDEX('Journal'!$B$8:$B$2007,$H65)) | C65: =IF($H65="","",INDEX('Journal'!$C$8:$C$2007,$H65)) | D65: =IF($H65="","",INDEX('Journal'!$F$8:$F$2007,$H65)) | E65: =IF($H65="","",INDEX('Journal'!$H$8:$H$2007,$H65)) | F65: =IF($H65="","",INDEX('Journal'!$I$8:$I$2007,$H65)) | G65: =IF($H65="","",N(G64)+N(E65)-N(F65)) | H65: {=IFERROR(SMALL(IF('Journal'!$D$8:$D$2007=$C$5,ROW('Journal'!$D$8:$D$2007)-7),58),"")}
A66: =IF($H66="","",INDEX('Journal'!$A$8:$A$2007,$H66)) | B66: =IF($H66="","",INDEX('Journal'!$B$8:$B$2007,$H66)) | C66: =IF($H66="","",INDEX('Journal'!$C$8:$C$2007,$H66)) | D66: =IF($H66="","",INDEX('Journal'!$F$8:$F$2007,$H66)) | E66: =IF($H66="","",INDEX('Journal'!$H$8:$H$2007,$H66)) | F66: =IF($H66="","",INDEX('Journal'!$I$8:$I$2007,$H66)) | G66: =IF($H66="","",N(G65)+N(E66)-N(F66)) | H66: {=IFERROR(SMALL(IF('Journal'!$D$8:$D$2007=$C$5,ROW('Journal'!$D$8:$D$2007)-7),59),"")}
A67: =IF($H67="","",INDEX('Journal'!$A$8:$A$2007,$H67)) | B67: =IF($H67="","",INDEX('Journal'!$B$8:$B$2007,$H67)) | C67: =IF($H67="","",INDEX('Journal'!$C$8:$C$2007,$H67)) | D67: =IF($H67="","",INDEX('Journal'!$F$8:$F$2007,$H67)) | E67: =IF($H67="","",INDEX('Journal'!$H$8:$H$2007,$H67)) | F67: =IF($H67="","",INDEX('Journal'!$I$8:$I$2007,$H67)) | G67: =IF($H67="","",N(G66)+N(E67)-N(F67)) | H67: {=IFERROR(SMALL(IF('Journal'!$D$8:$D$2007=$C$5,ROW('Journal'!$D$8:$D$2007)-7),60),"")}
A68: =IF($H68="","",INDEX('Journal'!$A$8:$A$2007,$H68)) | B68: =IF($H68="","",INDEX('Journal'!$B$8:$B$2007,$H68)) | C68: =IF($H68="","",INDEX('Journal'!$C$8:$C$2007,$H68)) | D68: =IF($H68="","",INDEX('Journal'!$F$8:$F$2007,$H68)) | E68: =IF($H68="","",INDEX('Journal'!$H$8:$H$2007,$H68)) | F68: =IF($H68="","",INDEX('Journal'!$I$8:$I$2007,$H68)) | G68: =IF($H68="","",N(G67)+N(E68)-N(F68)) | H68: {=IFERROR(SMALL(IF('Journal'!$D$8:$D$2007=$C$5,ROW('Journal'!$D$8:$D$2007)-7),61),"")}
A69: =IF($H69="","",INDEX('Journal'!$A$8:$A$2007,$H69)) | B69: =IF($H69="","",INDEX('Journal'!$B$8:$B$2007,$H69)) | C69: =IF($H69="","",INDEX('Journal'!$C$8:$C$2007,$H69)) | D69: =IF($H69="","",INDEX('Journal'!$F$8:$F$2007,$H69)) | E69: =IF($H69="","",INDEX('Journal'!$H$8:$H$2007,$H69)) | F69: =IF($H69="","",INDEX('Journal'!$I$8:$I$2007,$H69)) | G69: =IF($H69="","",N(G68)+N(E69)-N(F69)) | H69: {=IFERROR(SMALL(IF('Journal'!$D$8:$D$2007=$C$5,ROW('Journal'!$D$8:$D$2007)-7),62),"")}
A70: =IF($H70="","",INDEX('Journal'!$A$8:$A$2007,$H70)) | B70: =IF($H70="","",INDEX('Journal'!$B$8:$B$2007,$H70)) | C70: =IF($H70="","",INDEX('Journal'!$C$8:$C$2007,$H70)) | D70: =IF($H70="","",INDEX('Journal'!$F$8:$F$2007,$H70)) | E70: =IF($H70="","",INDEX('Journal'!$H$8:$H$2007,$H70)) | F70: =IF($H70="","",INDEX('Journal'!$I$8:$I$2007,$H70)) | G70: =IF($H70="","",N(G69)+N(E70)-N(F70)) | H70: {=IFERROR(SMALL(IF('Journal'!$D$8:$D$2007=$C$5,ROW('Journal'!$D$8:$D$2007)-7),63),"")}
A71: =IF($H71="","",INDEX('Journal'!$A$8:$A$2007,$H71)) | B71: =IF($H71="","",INDEX('Journal'!$B$8:$B$2007,$H71)) | C71: =IF($H71="","",INDEX('Journal'!$C$8:$C$2007,$H71)) | D71: =IF($H71="","",INDEX('Journal'!$F$8:$F$2007,$H71)) | E71: =IF($H71="","",INDEX('Journal'!$H$8:$H$2007,$H71)) | F71: =IF($H71="","",INDEX('Journal'!$I$8:$I$2007,$H71)) | G71: =IF($H71="","",N(G70)+N(E71)-N(F71)) | H71: {=IFERROR(SMALL(IF('Journal'!$D$8:$D$2007=$C$5,ROW('Journal'!$D$8:$D$2007)-7),64),"")}
A72: =IF($H72="","",INDEX('Journal'!$A$8:$A$2007,$H72)) | B72: =IF($H72="","",INDEX('Journal'!$B$8:$B$2007,$H72)) | C72: =IF($H72="","",INDEX('Journal'!$C$8:$C$2007,$H72)) | D72: =IF($H72="","",INDEX('Journal'!$F$8:$F$2007,$H72)) | E72: =IF($H72="","",INDEX('Journal'!$H$8:$H$2007,$H72)) | F72: =IF($H72="","",INDEX('Journal'!$I$8:$I$2007,$H72)) | G72: =IF($H72="","",N(G71)+N(E72)-N(F72)) | H72: {=IFERROR(SMALL(IF('Journal'!$D$8:$D$2007=$C$5,ROW('Journal'!$D$8:$D$2007)-7),65),"")}
A73: =IF($H73="","",INDEX('Journal'!$A$8:$A$2007,$H73)) | B73: =IF($H73="","",INDEX('Journal'!$B$8:$B$2007,$H73)) | C73: =IF($H73="","",INDEX('Journal'!$C$8:$C$2007,$H73)) | D73: =IF($H73="","",INDEX('Journal'!$F$8:$F$2007,$H73)) | E73: =IF($H73="","",INDEX('Journal'!$H$8:$H$2007,$H73)) | F73: =IF($H73="","",INDEX('Journal'!$I$8:$I$2007,$H73)) | G73: =IF($H73="","",N(G72)+N(E73)-N(F73)) | H73: {=IFERROR(SMALL(IF('Journal'!$D$8:$D$2007=$C$5,ROW('Journal'!$D$8:$D$2007)-7),66),"")}
A74: =IF($H74="","",INDEX('Journal'!$A$8:$A$2007,$H74)) | B74: =IF($H74="","",INDEX('Journal'!$B$8:$B$2007,$H74)) | C74: =IF($H74="","",INDEX('Journal'!$C$8:$C$2007,$H74)) | D74: =IF($H74="","",INDEX('Journal'!$F$8:$F$2007,$H74)) | E74: =IF($H74="","",INDEX('Journal'!$H$8:$H$2007,$H74)) | F74: =IF($H74="","",INDEX('Journal'!$I$8:$I$2007,$H74)) | G74: =IF($H74="","",N(G73)+N(E74)-N(F74)) | H74: {=IFERROR(SMALL(IF('Journal'!$D$8:$D$2007=$C$5,ROW('Journal'!$D$8:$D$2007)-7),67),"")}
A75: =IF($H75="","",INDEX('Journal'!$A$8:$A$2007,$H75)) | B75: =IF($H75="","",INDEX('Journal'!$B$8:$B$2007,$H75)) | C75: =IF($H75="","",INDEX('Journal'!$C$8:$C$2007,$H75)) | D75: =IF($H75="","",INDEX('Journal'!$F$8:$F$2007,$H75)) | E75: =IF($H75="","",INDEX('Journal'!$H$8:$H$2007,$H75)) | F75: =IF($H75="","",INDEX('Journal'!$I$8:$I$2007,$H75)) | G75: =IF($H75="","",N(G74)+N(E75)-N(F75)) | H75: {=IFERROR(SMALL(IF('Journal'!$D$8:$D$2007=$C$5,ROW('Journal'!$D$8:$D$2007)-7),68),"")}
A76: =IF($H76="","",INDEX('Journal'!$A$8:$A$2007,$H76)) | B76: =IF($H76="","",INDEX('Journal'!$B$8:$B$2007,$H76)) | C76: =IF($H76="","",INDEX('Journal'!$C$8:$C$2007,$H76)) | D76: =IF($H76="","",INDEX('Journal'!$F$8:$F$2007,$H76)) | E76: =IF($H76="","",INDEX('Journal'!$H$8:$H$2007,$H76)) | F76: =IF($H76="","",INDEX('Journal'!$I$8:$I$2007,$H76)) | G76: =IF($H76="","",N(G75)+N(E76)-N(F76)) | H76: {=IFERROR(SMALL(IF('Journal'!$D$8:$D$2007=$C$5,ROW('Journal'!$D$8:$D$2007)-7),69),"")}
A77: =IF($H77="","",INDEX('Journal'!$A$8:$A$2007,$H77)) | B77: =IF($H77="","",INDEX('Journal'!$B$8:$B$2007,$H77)) | C77: =IF($H77="","",INDEX('Journal'!$C$8:$C$2007,$H77)) | D77: =IF($H77="","",INDEX('Journal'!$F$8:$F$2007,$H77)) | E77: =IF($H77="","",INDEX('Journal'!$H$8:$H$2007,$H77)) | F77: =IF($H77="","",INDEX('Journal'!$I$8:$I$2007,$H77)) | G77: =IF($H77="","",N(G76)+N(E77)-N(F77)) | H77: {=IFERROR(SMALL(IF('Journal'!$D$8:$D$2007=$C$5,ROW('Journal'!$D$8:$D$2007)-7),70),"")}
A78: =IF($H78="","",INDEX('Journal'!$A$8:$A$2007,$H78)) | B78: =IF($H78="","",INDEX('Journal'!$B$8:$B$2007,$H78)) | C78: =IF($H78="","",INDEX('Journal'!$C$8:$C$2007,$H78)) | D78: =IF($H78="","",INDEX('Journal'!$F$8:$F$2007,$H78)) | E78: =IF($H78="","",INDEX('Journal'!$H$8:$H$2007,$H78)) | F78: =IF($H78="","",INDEX('Journal'!$I$8:$I$2007,$H78)) | G78: =IF($H78="","",N(G77)+N(E78)-N(F78)) | H78: {=IFERROR(SMALL(IF('Journal'!$D$8:$D$2007=$C$5,ROW('Journal'!$D$8:$D$2007)-7),71),"")}
A79: =IF($H79="","",INDEX('Journal'!$A$8:$A$2007,$H79)) | B79: =IF($H79="","",INDEX('Journal'!$B$8:$B$2007,$H79)) | C79: =IF($H79="","",INDEX('Journal'!$C$8:$C$2007,$H79)) | D79: =IF($H79="","",INDEX('Journal'!$F$8:$F$2007,$H79)) | E79: =IF($H79="","",INDEX('Journal'!$H$8:$H$2007,$H79)) | F79: =IF($H79="","",INDEX('Journal'!$I$8:$I$2007,$H79)) | G79: =IF($H79="","",N(G78)+N(E79)-N(F79)) | H79: {=IFERROR(SMALL(IF('Journal'!$D$8:$D$2007=$C$5,ROW('Journal'!$D$8:$D$2007)-7),72),"")}
A80: =IF($H80="","",INDEX('Journal'!$A$8:$A$2007,$H80)) | B80: =IF($H80="","",INDEX('Journal'!$B$8:$B$2007,$H80)) | C80: =IF($H80="","",INDEX('Journal'!$C$8:$C$2007,$H80)) | D80: =IF($H80="","",INDEX('Journal'!$F$8:$F$2007,$H80)) | E80: =IF($H80="","",INDEX('Journal'!$H$8:$H$2007,$H80)) | F80: =IF($H80="","",INDEX('Journal'!$I$8:$I$2007,$H80)) | G80: =IF($H80="","",N(G79)+N(E80)-N(F80)) | H80: {=IFERROR(SMALL(IF('Journal'!$D$8:$D$2007=$C$5,ROW('Journal'!$D$8:$D$2007)-7),73),"")}
A81: =IF($H81="","",INDEX('Journal'!$A$8:$A$2007,$H81)) | B81: =IF($H81="","",INDEX('Journal'!$B$8:$B$2007,$H81)) | C81: =IF($H81="","",INDEX('Journal'!$C$8:$C$2007,$H81)) | D81: =IF($H81="","",INDEX('Journal'!$F$8:$F$2007,$H81)) | E81: =IF($H81="","",INDEX('Journal'!$H$8:$H$2007,$H81)) | F81: =IF($H81="","",INDEX('Journal'!$I$8:$I$2007,$H81)) | G81: =IF($H81="","",N(G80)+N(E81)-N(F81)) | H81: {=IFERROR(SMALL(IF('Journal'!$D$8:$D$2007=$C$5,ROW('Journal'!$D$8:$D$2007)-7),74),"")}
A82: =IF($H82="","",INDEX('Journal'!$A$8:$A$2007,$H82)) | B82: =IF($H82="","",INDEX('Journal'!$B$8:$B$2007,$H82)) | C82: =IF($H82="","",INDEX('Journal'!$C$8:$C$2007,$H82)) | D82: =IF($H82="","",INDEX('Journal'!$F$8:$F$2007,$H82)) | E82: =IF($H82="","",INDEX('Journal'!$H$8:$H$2007,$H82)) | F82: =IF($H82="","",INDEX('Journal'!$I$8:$I$2007,$H82)) | G82: =IF($H82="","",N(G81)+N(E82)-N(F82)) | H82: {=IFERROR(SMALL(IF('Journal'!$D$8:$D$2007=$C$5,ROW('Journal'!$D$8:$D$2007)-7),75),"")}
A83: =IF($H83="","",INDEX('Journal'!$A$8:$A$2007,$H83)) | B83: =IF($H83="","",INDEX('Journal'!$B$8:$B$2007,$H83)) | C83: =IF($H83="","",INDEX('Journal'!$C$8:$C$2007,$H83)) | D83: =IF($H83="","",INDEX('Journal'!$F$8:$F$2007,$H83)) | E83: =IF($H83="","",INDEX('Journal'!$H$8:$H$2007,$H83)) | F83: =IF($H83="","",INDEX('Journal'!$I$8:$I$2007,$H83)) | G83: =IF($H83="","",N(G82)+N(E83)-N(F83)) | H83: {=IFERROR(SMALL(IF('Journal'!$D$8:$D$2007=$C$5,ROW('Journal'!$D$8:$D$2007)-7),76),"")}
A84: =IF($H84="","",INDEX('Journal'!$A$8:$A$2007,$H84)) | B84: =IF($H84="","",INDEX('Journal'!$B$8:$B$2007,$H84)) | C84: =IF($H84="","",INDEX('Journal'!$C$8:$C$2007,$H84)) | D84: =IF($H84="","",INDEX('Journal'!$F$8:$F$2007,$H84)) | E84: =IF($H84="","",INDEX('Journal'!$H$8:$H$2007,$H84)) | F84: =IF($H84="","",INDEX('Journal'!$I$8:$I$2007,$H84)) | G84: =IF($H84="","",N(G83)+N(E84)-N(F84)) | H84: {=IFERROR(SMALL(IF('Journal'!$D$8:$D$2007=$C$5,ROW('Journal'!$D$8:$D$2007)-7),77),"")}
A85: =IF($H85="","",INDEX('Journal'!$A$8:$A$2007,$H85)) | B85: =IF($H85="","",INDEX('Journal'!$B$8:$B$2007,$H85)) | C85: =IF($H85="","",INDEX('Journal'!$C$8:$C$2007,$H85)) | D85: =IF($H85="","",INDEX('Journal'!$F$8:$F$2007,$H85)) | E85: =IF($H85="","",INDEX('Journal'!$H$8:$H$2007,$H85)) | F85: =IF($H85="","",INDEX('Journal'!$I$8:$I$2007,$H85)) | G85: =IF($H85="","",N(G84)+N(E85)-N(F85)) | H85: {=IFERROR(SMALL(IF('Journal'!$D$8:$D$2007=$C$5,ROW('Journal'!$D$8:$D$2007)-7),78),"")}
A86: =IF($H86="","",INDEX('Journal'!$A$8:$A$2007,$H86)) | B86: =IF($H86="","",INDEX('Journal'!$B$8:$B$2007,$H86)) | C86: =IF($H86="","",INDEX('Journal'!$C$8:$C$2007,$H86)) | D86: =IF($H86="","",INDEX('Journal'!$F$8:$F$2007,$H86)) | E86: =IF($H86="","",INDEX('Journal'!$H$8:$H$2007,$H86)) | F86: =IF($H86="","",INDEX('Journal'!$I$8:$I$2007,$H86)) | G86: =IF($H86="","",N(G85)+N(E86)-N(F86)) | H86: {=IFERROR(SMALL(IF('Journal'!$D$8:$D$2007=$C$5,ROW('Journal'!$D$8:$D$2007)-7),79),"")}
A87: =IF($H87="","",INDEX('Journal'!$A$8:$A$2007,$H87)) | B87: =IF($H87="","",INDEX('Journal'!$B$8:$B$2007,$H87)) | C87: =IF($H87="","",INDEX('Journal'!$C$8:$C$2007,$H87)) | D87: =IF($H87="","",INDEX('Journal'!$F$8:$F$2007,$H87)) | E87: =IF($H87="","",INDEX('Journal'!$H$8:$H$2007,$H87)) | F87: =IF($H87="","",INDEX('Journal'!$I$8:$I$2007,$H87)) | G87: =IF($H87="","",N(G86)+N(E87)-N(F87)) | H87: {=IFERROR(SMALL(IF('Journal'!$D$8:$D$2007=$C$5,ROW('Journal'!$D$8:$D$2007)-7),80),"")}
A88: =IF($H88="","",INDEX('Journal'!$A$8:$A$2007,$H88)) | B88: =IF($H88="","",INDEX('Journal'!$B$8:$B$2007,$H88)) | C88: =IF($H88="","",INDEX('Journal'!$C$8:$C$2007,$H88)) | D88: =IF($H88="","",INDEX('Journal'!$F$8:$F$2007,$H88)) | E88: =IF($H88="","",INDEX('Journal'!$H$8:$H$2007,$H88)) | F88: =IF($H88="","",INDEX('Journal'!$I$8:$I$2007,$H88)) | G88: =IF($H88="","",N(G87)+N(E88)-N(F88)) | H88: {=IFERROR(SMALL(IF('Journal'!$D$8:$D$2007=$C$5,ROW('Journal'!$D$8:$D$2007)-7),81),"")}
A89: =IF($H89="","",INDEX('Journal'!$A$8:$A$2007,$H89)) | B89: =IF($H89="","",INDEX('Journal'!$B$8:$B$2007,$H89)) | C89: =IF($H89="","",INDEX('Journal'!$C$8:$C$2007,$H89)) | D89: =IF($H89="","",INDEX('Journal'!$F$8:$F$2007,$H89)) | E89: =IF($H89="","",INDEX('Journal'!$H$8:$H$2007,$H89)) | F89: =IF($H89="","",INDEX('Journal'!$I$8:$I$2007,$H89)) | G89: =IF($H89="","",N(G88)+N(E89)-N(F89)) | H89: {=IFERROR(SMALL(IF('Journal'!$D$8:$D$2007=$C$5,ROW('Journal'!$D$8:$D$2007)-7),82),"")}
A90: =IF($H90="","",INDEX('Journal'!$A$8:$A$2007,$H90)) | B90: =IF($H90="","",INDEX('Journal'!$B$8:$B$2007,$H90)) | C90: =IF($H90="","",INDEX('Journal'!$C$8:$C$2007,$H90)) | D90: =IF($H90="","",INDEX('Journal'!$F$8:$F$2007,$H90)) | E90: =IF($H90="","",INDEX('Journal'!$H$8:$H$2007,$H90)) | F90: =IF($H90="","",INDEX('Journal'!$I$8:$I$2007,$H90)) | G90: =IF($H90="","",N(G89)+N(E90)-N(F90)) | H90: {=IFERROR(SMALL(IF('Journal'!$D$8:$D$2007=$C$5,ROW('Journal'!$D$8:$D$2007)-7),83),"")}
A91: =IF($H91="","",INDEX('Journal'!$A$8:$A$2007,$H91)) | B91: =IF($H91="","",INDEX('Journal'!$B$8:$B$2007,$H91)) | C91: =IF($H91="","",INDEX('Journal'!$C$8:$C$2007,$H91)) | D91: =IF($H91="","",INDEX('Journal'!$F$8:$F$2007,$H91)) | E91: =IF($H91="","",INDEX('Journal'!$H$8:$H$2007,$H91)) | F91: =IF($H91="","",INDEX('Journal'!$I$8:$I$2007,$H91)) | G91: =IF($H91="","",N(G90)+N(E91)-N(F91)) | H91: {=IFERROR(SMALL(IF('Journal'!$D$8:$D$2007=$C$5,ROW('Journal'!$D$8:$D$2007)-7),84),"")}
A92: =IF($H92="","",INDEX('Journal'!$A$8:$A$2007,$H92)) | B92: =IF($H92="","",INDEX('Journal'!$B$8:$B$2007,$H92)) | C92: =IF($H92="","",INDEX('Journal'!$C$8:$C$2007,$H92)) | D92: =IF($H92="","",INDEX('Journal'!$F$8:$F$2007,$H92)) | E92: =IF($H92="","",INDEX('Journal'!$H$8:$H$2007,$H92)) | F92: =IF($H92="","",INDEX('Journal'!$I$8:$I$2007,$H92)) | G92: =IF($H92="","",N(G91)+N(E92)-N(F92)) | H92: {=IFERROR(SMALL(IF('Journal'!$D$8:$D$2007=$C$5,ROW('Journal'!$D$8:$D$2007)-7),85),"")}
A93: =IF($H93="","",INDEX('Journal'!$A$8:$A$2007,$H93)) | B93: =IF($H93="","",INDEX('Journal'!$B$8:$B$2007,$H93)) | C93: =IF($H93="","",INDEX('Journal'!$C$8:$C$2007,$H93)) | D93: =IF($H93="","",INDEX('Journal'!$F$8:$F$2007,$H93)) | E93: =IF($H93="","",INDEX('Journal'!$H$8:$H$2007,$H93)) | F93: =IF($H93="","",INDEX('Journal'!$I$8:$I$2007,$H93)) | G93: =IF($H93="","",N(G92)+N(E93)-N(F93)) | H93: {=IFERROR(SMALL(IF('Journal'!$D$8:$D$2007=$C$5,ROW('Journal'!$D$8:$D$2007)-7),86),"")}
A94: =IF($H94="","",INDEX('Journal'!$A$8:$A$2007,$H94)) | B94: =IF($H94="","",INDEX('Journal'!$B$8:$B$2007,$H94)) | C94: =IF($H94="","",INDEX('Journal'!$C$8:$C$2007,$H94)) | D94: =IF($H94="","",INDEX('Journal'!$F$8:$F$2007,$H94)) | E94: =IF($H94="","",INDEX('Journal'!$H$8:$H$2007,$H94)) | F94: =IF($H94="","",INDEX('Journal'!$I$8:$I$2007,$H94)) | G94: =IF($H94="","",N(G93)+N(E94)-N(F94)) | H94: {=IFERROR(SMALL(IF('Journal'!$D$8:$D$2007=$C$5,ROW('Journal'!$D$8:$D$2007)-7),87),"")}
A95: =IF($H95="","",INDEX('Journal'!$A$8:$A$2007,$H95)) | B95: =IF($H95="","",INDEX('Journal'!$B$8:$B$2007,$H95)) | C95: =IF($H95="","",INDEX('Journal'!$C$8:$C$2007,$H95)) | D95: =IF($H95="","",INDEX('Journal'!$F$8:$F$2007,$H95)) | E95: =IF($H95="","",INDEX('Journal'!$H$8:$H$2007,$H95)) | F95: =IF($H95="","",INDEX('Journal'!$I$8:$I$2007,$H95)) | G95: =IF($H95="","",N(G94)+N(E95)-N(F95)) | H95: {=IFERROR(SMALL(IF('Journal'!$D$8:$D$2007=$C$5,ROW('Journal'!$D$8:$D$2007)-7),88),"")}
A96: =IF($H96="","",INDEX('Journal'!$A$8:$A$2007,$H96)) | B96: =IF($H96="","",INDEX('Journal'!$B$8:$B$2007,$H96)) | C96: =IF($H96="","",INDEX('Journal'!$C$8:$C$2007,$H96)) | D96: =IF($H96="","",INDEX('Journal'!$F$8:$F$2007,$H96)) | E96: =IF($H96="","",INDEX('Journal'!$H$8:$H$2007,$H96)) | F96: =IF($H96="","",INDEX('Journal'!$I$8:$I$2007,$H96)) | G96: =IF($H96="","",N(G95)+N(E96)-N(F96)) | H96: {=IFERROR(SMALL(IF('Journal'!$D$8:$D$2007=$C$5,ROW('Journal'!$D$8:$D$2007)-7),89),"")}
A97: =IF($H97="","",INDEX('Journal'!$A$8:$A$2007,$H97)) | B97: =IF($H97="","",INDEX('Journal'!$B$8:$B$2007,$H97)) | C97: =IF($H97="","",INDEX('Journal'!$C$8:$C$2007,$H97)) | D97: =IF($H97="","",INDEX('Journal'!$F$8:$F$2007,$H97)) | E97: =IF($H97="","",INDEX('Journal'!$H$8:$H$2007,$H97)) | F97: =IF($H97="","",INDEX('Journal'!$I$8:$I$2007,$H97)) | G97: =IF($H97="","",N(G96)+N(E97)-N(F97)) | H97: {=IFERROR(SMALL(IF('Journal'!$D$8:$D$2007=$C$5,ROW('Journal'!$D$8:$D$2007)-7),90),"")}
A98: =IF($H98="","",INDEX('Journal'!$A$8:$A$2007,$H98)) | B98: =IF($H98="","",INDEX('Journal'!$B$8:$B$2007,$H98)) | C98: =IF($H98="","",INDEX('Journal'!$C$8:$C$2007,$H98)) | D98: =IF($H98="","",INDEX('Journal'!$F$8:$F$2007,$H98)) | E98: =IF($H98="","",INDEX('Journal'!$H$8:$H$2007,$H98)) | F98: =IF($H98="","",INDEX('Journal'!$I$8:$I$2007,$H98)) | G98: =IF($H98="","",N(G97)+N(E98)-N(F98)) | H98: {=IFERROR(SMALL(IF('Journal'!$D$8:$D$2007=$C$5,ROW('Journal'!$D$8:$D$2007)-7),91),"")}
A99: =IF($H99="","",INDEX('Journal'!$A$8:$A$2007,$H99)) | B99: =IF($H99="","",INDEX('Journal'!$B$8:$B$2007,$H99)) | C99: =IF($H99="","",INDEX('Journal'!$C$8:$C$2007,$H99)) | D99: =IF($H99="","",INDEX('Journal'!$F$8:$F$2007,$H99)) | E99: =IF($H99="","",INDEX('Journal'!$H$8:$H$2007,$H99)) | F99: =IF($H99="","",INDEX('Journal'!$I$8:$I$2007,$H99)) | G99: =IF($H99="","",N(G98)+N(E99)-N(F99)) | H99: {=IFERROR(SMALL(IF('Journal'!$D$8:$D$2007=$C$5,ROW('Journal'!$D$8:$D$2007)-7),92),"")}
A100: =IF($H100="","",INDEX('Journal'!$A$8:$A$2007,$H100)) | B100: =IF($H100="","",INDEX('Journal'!$B$8:$B$2007,$H100)) | C100: =IF($H100="","",INDEX('Journal'!$C$8:$C$2007,$H100)) | D100: =IF($H100="","",INDEX('Journal'!$F$8:$F$2007,$H100)) | E100: =IF($H100="","",INDEX('Journal'!$H$8:$H$2007,$H100)) | F100: =IF($H100="","",INDEX('Journal'!$I$8:$I$2007,$H100)) | G100: =IF($H100="","",N(G99)+N(E100)-N(F100)) | H100: {=IFERROR(SMALL(IF('Journal'!$D$8:$D$2007=$C$5,ROW('Journal'!$D$8:$D$2007)-7),93),"")}
A101: =IF($H101="","",INDEX('Journal'!$A$8:$A$2007,$H101)) | B101: =IF($H101="","",INDEX('Journal'!$B$8:$B$2007,$H101)) | C101: =IF($H101="","",INDEX('Journal'!$C$8:$C$2007,$H101)) | D101: =IF($H101="","",INDEX('Journal'!$F$8:$F$2007,$H101)) | E101: =IF($H101="","",INDEX('Journal'!$H$8:$H$2007,$H101)) | F101: =IF($H101="","",INDEX('Journal'!$I$8:$I$2007,$H101)) | G101: =IF($H101="","",N(G100)+N(E101)-N(F101)) | H101: {=IFERROR(SMALL(IF('Journal'!$D$8:$D$2007=$C$5,ROW('Journal'!$D$8:$D$2007)-7),94),"")}
...

Sheet Balance
A1: BALANCE GÉNÉRALE
A2: ميزان المراجعة
A3: =Societe&" · Exercice "&Exercice
A5: =IF(ROUND(SUM(C8:C192)-SUM(D8:D192),2)=0,"Balance équilibrée : total débit = total crédit.","Balance déséquilibrée — écart de "&TEXT(SUM(C8:C192)-SUM(D8:D192),"#,##0.00")&" DA. Une écriture du journal ne se boucle pas.")
A7: Compte | B7: Intitulé | C7: Mouvement débit | D7: Mouvement crédit | E7: Solde débiteur | F7: Solde créditeur | G7: Solde signé | H7: Rubrique | I7: Déd. | J7: Cl. | K7: Préf. 2 | L7: Préf. 3
A8: 101 | B8: Capital émis (capital social, fonds de dotation) | C8: =SUMIF('Journal'!$D$8:$D$2007,$A8,'Journal'!$H$8:$H$2007) | D8: =SUMIF('Journal'!$D$8:$D$2007,$A8,'Journal'!$I$8:$I$2007) | E8: =IF($C8-$D8>0,$C8-$D8,0) | F8: =IF($D8-$C8>0,$D8-$C8,0) | G8: =$C8-$D8 | H8: CP_CAP | I8: 0 | J8: 1 | K8: 10 | L8: 101
A9: 103 | B9: Primes liées au capital social | C9: =SUMIF('Journal'!$D$8:$D$2007,$A9,'Journal'!$H$8:$H$2007) | D9: =SUMIF('Journal'!$D$8:$D$2007,$A9,'Journal'!$I$8:$I$2007) | E9: =IF($C9-$D9>0,$C9-$D9,0) | F9: =IF($D9-$C9>0,$D9-$C9,0) | G9: =$C9-$D9 | H9: CP_PRI | I9: 0 | J9: 1 | K9: 10 | L9: 103
A10: 104 | B10: Écart d'évaluation | C10: =SUMIF('Journal'!$D$8:$D$2007,$A10,'Journal'!$H$8:$H$2007) | D10: =SUMIF('Journal'!$D$8:$D$2007,$A10,'Journal'!$I$8:$I$2007) | E10: =IF($C10-$D10>0,$C10-$D10,0) | F10: =IF($D10-$C10>0,$D10-$C10,0) | G10: =$C10-$D10 | H10: CP_PRI | I10: 0 | J10: 1 | K10: 10 | L10: 104
A11: 105 | B11: Écart de réévaluation | C11: =SUMIF('Journal'!$D$8:$D$2007,$A11,'Journal'!$H$8:$H$2007) | D11: =SUMIF('Journal'!$D$8:$D$2007,$A11,'Journal'!$I$8:$I$2007) | E11: =IF($C11-$D11>0,$C11-$D11,0) | F11: =IF($D11-$C11>0,$D11-$C11,0) | G11: =$C11-$D11 | H11: CP_REE | I11: 0 | J11: 1 | K11: 10 | L11: 105
A12: 106 | B12: Réserves (légale, statutaire, ordinaire, réglementée) | C12: =SUMIF('Journal'!$D$8:$D$2007,$A12,'Journal'!$H$8:$H$2007) | D12: =SUMIF('Journal'!$D$8:$D$2007,$A12,'Journal'!$I$8:$I$2007) | E12: =IF($C12-$D12>0,$C12-$D12,0) | F12: =IF($D12-$C12>0,$D12-$C12,0) | G12: =$C12-$D12 | H12: CP_PRI | I12: 0 | J12: 1 | K12: 10 | L12: 106
A13: 107 | B13: Écart d'équivalence | C13: =SUMIF('Journal'!$D$8:$D$2007,$A13,'Journal'!$H$8:$H$2007) | D13: =SUMIF('Journal'!$D$8:$D$2007,$A13,'Journal'!$I$8:$I$2007) | E13: =IF($C13-$D13>0,$C13-$D13,0) | F13: =IF($D13-$C13>0,$D13-$C13,0) | G13: =$C13-$D13 | H13: CP_EQU | I13: 0 | J13: 1 | K13: 10 | L13: 107
A14: 108 | B14: Compte de l'exploitant | C14: =SUMIF('Journal'!$D$8:$D$2007,$A14,'Journal'!$H$8:$H$2007) | D14: =SUMIF('Journal'!$D$8:$D$2007,$A14,'Journal'!$I$8:$I$2007) | E14: =IF($C14-$D14>0,$C14-$D14,0) | F14: =IF($D14-$C14>0,$D14-$C14,0) | G14: =$C14-$D14 | H14: CP_ART | I14: 0 | J14: 1 | K14: 10 | L14: 108
A15: 109 | B15: Capital souscrit non appelé | C15: =SUMIF('Journal'!$D$8:$D$2007,$A15,'Journal'!$H$8:$H$2007) | D15: =SUMIF('Journal'!$D$8:$D$2007,$A15,'Journal'!$I$8:$I$2007) | E15: =IF($C15-$D15>0,$C15-$D15,0) | F15: =IF($D15-$C15>0,$D15-$C15,0) | G15: =$C15-$D15 | H15: CP_NAP | I15: 0 | J15: 1 | K15: 10 | L15: 109
A16: 110 | B16: Report à nouveau (solde créditeur) | C16: =SUMIF('Journal'!$D$8:$D$2007,$A16,'Journal'!$H$8:$H$2007) | D16: =SUMIF('Journal'!$D$8:$D$2007,$A16,'Journal'!$I$8:$I$2007) | E16: =IF($C16-$D16>0,$C16-$D16,0) | F16: =IF($D16-$C16>0,$D16-$C16,0) | G16: =$C16-$D16 | H16: CP_ART | I16: 0 | J16: 1 | K16: 11 | L16: 110
A17: 119 | B17: Report à nouveau (solde débiteur) | C17: =SUMIF('Journal'!$D$8:$D$2007,$A17,'Journal'!$H$8:$H$2007) | D17: =SUMIF('Journal'!$D$8:$D$2007,$A17,'Journal'!$I$8:$I$2007) | E17: =IF($C17-$D17>0,$C17-$D17,0) | F17: =IF($D17-$C17>0,$D17-$C17,0) | G17: =$C17-$D17 | H17: CP_ART | I17: 0 | J17: 1 | K17: 11 | L17: 119
A18: 120 | B18: Résultat de l'exercice (bénéfice) | C18: =SUMIF('Journal'!$D$8:$D$2007,$A18,'Journal'!$H$8:$H$2007) | D18: =SUMIF('Journal'!$D$8:$D$2007,$A18,'Journal'!$I$8:$I$2007) | E18: =IF($C18-$D18>0,$C18-$D18,0) | F18: =IF($D18-$C18>0,$D18-$C18,0) | G18: =$C18-$D18 | H18: CP_RES | I18: 0 | J18: 1 | K18: 12 | L18: 120
A19: 129 | B19: Résultat de l'exercice (perte) | C19: =SUMIF('Journal'!$D$8:$D$2007,$A19,'Journal'!$H$8:$H$2007) | D19: =SUMIF('Journal'!$D$8:$D$2007,$A19,'Journal'!$I$8:$I$2007) | E19: =IF($C19-$D19>0,$C19-$D19,0) | F19: =IF($D19-$C19>0,$D19-$C19,0) | G19: =$C19-$D19 | H19: CP_RES | I19: 0 | J19: 1 | K19: 12 | L19: 129
... A118: 59 | B118: Pertes de valeur sur actifs financiers courants | C118: =SUMIF('Journal'!$D$8:$D$2007,$A118,'Journal'!$H$8:$H$2007) | D118: =SUMIF('Journal'!$D$8:$D$2007,$A118,'Journal'!$I$8:$I$2007) | E118: =IF($C118-$D118>0,$C118-$D118,0) | F118: =IF($D118-$C118>0,$D118-$C118,0) | G118: =$C118-$D118 | H118: AC_PLA | I118: 1 | J118: 5 | K118: 59 | L118: 59
A119: 600 | B119: Achats de marchandises vendues | C119: =SUMIF('Journal'!$D$8:$D$2007,$A119,'Journal'!$H$8:$H$2007) | D119: =SUMIF('Journal'!$D$8:$D$2007,$A119,'Journal'!$I$8:$I$2007) | E119: =IF($C119-$D119>0,$C119-$D119,0) | F119: =IF($D119-$C119>0,$D119-$C119,0) | G119: =$C119-$D119 | I119: 0 | J119: 6 | K119: 60 | L119: 600
A120: 601 | B120: Matières premières | C120: =SUMIF('Journal'!$D$8:$D$2007,$A120,'Journal'!$H$8:$H$2007) | D120: =SUMIF('Journal'!$D$8:$D$2007,$A120,'Journal'!$I$8:$I$2007) | E120: =IF($C120-$D120>0,$C120-$D120,0) | F120: =IF($D120-$C120>0,$D120-$C120,0) | G120: =$C120-$D120 | I120: 0 | J120: 6 | K120: 60 | L120: 601
A121: 602 | B121: Autres approvisionnements | C121: =SUMIF('Journal'!$D$8:$D$2007,$A121,'Journal'!$H$8:$H$2007) | D121: =SUMIF('Journal'!$D$8:$D$2007,$A121,'Journal'!$I$8:$I$2007) | E121: =IF($C121-$D121>0,$C121-$D121,0) | F121: =IF($D121-$C121>0,$D121-$C121,0) | G121: =$C121-$D121 | I121: 0 | J121: 6 | K121: 60 | L121: 602
A122: 603 | B122: Variation des stocks | C122: =SUMIF('Journal'!$D$8:$D$2007,$A122,'Journal'!$H$8:$H$2007) | D122: =SUMIF('Journal'!$D$8:$D$2007,$A122,'Journal'!$I$8:$I$2007) | E122: =IF($C122-$D122>0,$C122-$D122,0) | F122: =IF($D122-$C122>0,$D122-$C122,0) | G122: =$C122-$D122 | I122: 0 | J122: 6 | K122: 60 | L122: 603
A123: 604 | B123: Achats d'études et de prestations de services | C123: =SUMIF('Journal'!$D$8:$D$2007,$A123,'Journal'!$H$8:$H$2007) | D123: =SUMIF('Journal'!$D$8:$D$2007,$A123,'Journal'!$I$8:$I$2007) | E123: =IF($C123-$D123>0,$C123-$D123,0) | F123: =IF($D123-$C123>0,$D123-$C123,0) | G123: =$C123-$D123 | I123: 0 | J123: 6 | K123: 60 | L123: 604
A124: 605 | B124: Achats de matériels, équipements et travaux | C124: =SUMIF('Journal'!$D$8:$D$2007,$A124,'Journal'!$H$8:$H$2007) | D124: =SUMIF('Journal'!$D$8:$D$2007,$A124,'Journal'!$I$8:$I$2007) | E124: =IF($C124-$D124>0,$C124-$D124,0) | F124: =IF($D124-$C124>0,$D124-$C124,0) | G124: =$C124-$D124 | I124: 0 | J124: 6 | K124: 60 | L124: 605
A125: 607 | B125: Achats non stockés de matières et fournitures | C125: =SUMIF('Journal'!$D$8:$D$2007,$A125,'Journal'!$H$8:$H$2007) | D125: =SUMIF('Journal'!$D$8:$D$2007,$A125,'Journal'!$I$8:$I$2007) | E125: =IF($C125-$D125>0,$C125-$D125,0) | F125: =IF($D125-$C125>0,$D125-$C125,0) | G125: =$C125-$D125 | I125: 0 | J125: 6 | K125: 60 | L125: 607
A126: 608 | B126: Frais accessoires d'achat | C126: =SUMIF('Journal'!$D$8:$D$2007,$A126,'Journal'!$H$8:$H$2007) | D126: =SUMIF('Journal'!$D$8:$D$2007,$A126,'Journal'!$I$8:$I$2007) | E126: =IF($C126-$D126>0,$C126-$D126,0) | F126: =IF($D126-$C126>0,$D126-$C126,0) | G126: =$C126-$D126 | I126: 0 | J126: 6 | K126: 60 | L126: 608
A127: 609 | B127: Rabais, remises et ristournes obtenus sur achats | C127: =SUMIF('Journal'!$D$8:$D$2007,$A127,'Journal'!$H$8:$H$2007) | D127: =SUMIF('Journal'!$D$8:$D$2007,$A127,'Journal'!$I$8:$I$2007) | E127: =IF($C127-$D127>0,$C127-$D127,0) | F127: =IF($D127-$C127>0,$D127-$C127,0) | G127: =$C127-$D127 | I127: 0 | J127: 6 | K127: 60 | L127: 609
A128: 611 | B128: Sous-traitance générale | C128: =SUMIF('Journal'!$D$8:$D$2007,$A128,'Journal'!$H$8:$H$2007) | D128: =SUMIF('Journal'!$D$8:$D$2007,$A128,'Journal'!$I$8:$I$2007) | E128: =IF($C128-$D128>0,$C128-$D128,0) | F128: =IF($D128-$C128>0,$D128-$C128,0) | G128: =$C128-$D128 | I128: 0 | J128: 6 | K128: 61 | L128: 611
A129: 613 | B129: Locations | C129: =SUMIF('Journal'!$D$8:$D$2007,$A129,'Journal'!$H$8:$H$2007) | D129: =SUMIF('Journal'!$D$8:$D$2007,$A129,'Journal'!$I$8:$I$2007) | E129: =IF($C129-$D129>0,$C129-$D129,0) | F129: =IF($D129-$C129>0,$D129-$C129,0) | G129: =$C129-$D129 | I129: 0 | J129: 6 | K129: 61 | L129: 613
A130: 614 | B130: Charges locatives et de copropriété | C130: =SUMIF('Journal'!$D$8:$D$2007,$A130,'Journal'!$H$8:$H$2007) | D130: =SUMIF('Journal'!$D$8:$D$2007,$A130,'Journal'!$I$8:$I$2007) | E130: =IF($C130-$D130>0,$C130-$D130,0) | F130: =IF($D130-$C130>0,$D130-$C130,0) | G130: =$C130-$D130 | I130: 0 | J130: 6 | K130: 61 | L130: 614
... A192: 786 | B192: Reprises — éléments financiers | C192: =SUMIF('Journal'!$D$8:$D$2007,$A192,'Journal'!$H$8:$H$2007) | D192: =SUMIF('Journal'!$D$8:$D$2007,$A192,'Journal'!$I$8:$I$2007) | E192: =IF($C192-$D192>0,$C192-$D192,0) | F192: =IF($D192-$C192>0,$D192-$C192,0) | G192: =$C192-$D192 | I192: 0 | J192: 7 | K192: 78 | L192: 786
A193: TOTAUX | C193: =SUM(C8:C192) | D193: =SUM(D8:D192) | E193: =SUM(E8:E192) | F193: =SUM(F8:F192) | G193: =SUM(G8:G192)
A194: Les six colonnes de droite servent au bilan et au compte de résultat. Elles ne se saisissent pas et ne se suppriment pas.

Sheet Coût des ventes
A1: COÛT DES VENTES ET MARGE
A2: تكلفة المبيعات والهامش
A3: =Societe&" · Exercice "&Exercice
A5: Deux lectures de la même chose. En haut, produit par produit, à partir de ce que vous saisissez ici. En bas, ce que disent les comptes du journal.
A7: PAR PRODUIT — حسب المنتج (cellules jaunes : à saisir)
A8: Désignation | B8: Quantité vendue | C8: Prix de vente HT | D8: Prix d'achat HT | E8: Ventes HT | F8: Coût d'achat | G8: Marge | H8: Taux
A9: Ciment CPJ 42.5 — sac 50 kg | B9: 400 | C9: 850 | D9: 620 | E9: =IF($A9="","",N($B9)*N($C9)) | F9: =IF($A9="","",N($B9)*N($D9)) | G9: =IF($A9="","",N($E9)-N($F9)) | H9: =IF(N($E9)=0,"",N($G9)/N($E9)*100)
A10: Rond à béton Ø10 — barre | B10: 120 | C10: 1250 | D10: 980 | E10: =IF($A10="","",N($B10)*N($C10)) | F10: =IF($A10="","",N($B10)*N($D10)) | G10: =IF($A10="","",N($E10)-N($F10)) | H10: =IF(N($E10)=0,"",N($G10)/N($E10)*100)
A11: Peinture intérieure — 20 L | B11: 35 | C11: 4200 | D11: 2950 | E11: =IF($A11="","",N($B11)*N($C11)) | F11: =IF($A11="","",N($B11)*N($D11)) | G11: =IF($A11="","",N($E11)-N($F11)) | H11: =IF(N($E11)=0,"",N($G11)/N($E11)*100)
E12: =IF($A12="","",N($B12)*N($C12)) | F12: =IF($A12="","",N($B12)*N($D12)) | G12: =IF($A12="","",N($E12)-N($F12)) | H12: =IF(N($E12)=0,"",N($G12)/N($E12)*100)
E13: =IF($A13="","",N($B13)*N($C13)) | F13: =IF($A13="","",N($B13)*N($D13)) | G13: =IF($A13="","",N($E13)-N($F13)) | H13: =IF(N($E13)=0,"",N($G13)/N($E13)*100)
E14: =IF($A14="","",N($B14)*N($C14)) | F14: =IF($A14="","",N($B14)*N($D14)) | G14: =IF($A14="","",N($E14)-N($F14)) | H14: =IF(N($E14)=0,"",N($G14)/N($E14)*100)
E15: =IF($A15="","",N($B15)*N($C15)) | F15: =IF($A15="","",N($B15)*N($D15)) | G15: =IF($A15="","",N($E15)-N($F15)) | H15: =IF(N($E15)=0,"",N($G15)/N($E15)*100)
E16: =IF($A16="","",N($B16)*N($C16)) | F16: =IF($A16="","",N($B16)*N($D16)) | G16: =IF($A16="","",N($E16)-N($F16)) | H16: =IF(N($E16)=0,"",N($G16)/N($E16)*100)
E17: =IF($A17="","",N($B17)*N($C17)) | F17: =IF($A17="","",N($B17)*N($D17)) | G17: =IF($A17="","",N($E17)-N($F17)) | H17: =IF(N($E17)=0,"",N($G17)/N($E17)*100)
E18: =IF($A18="","",N($B18)*N($C18)) | F18: =IF($A18="","",N($B18)*N($D18)) | G18: =IF($A18="","",N($E18)-N($F18)) | H18: =IF(N($E18)=0,"",N($G18)/N($E18)*100)
E19: =IF($A19="","",N($B19)*N($C19)) | F19: =IF($A19="","",N($B19)*N($D19)) | G19: =IF($A19="","",N($E19)-N($F19)) | H19: =IF(N($E19)=0,"",N($G19)/N($E19)*100)
E20: =IF($A20="","",N($B20)*N($C20)) | F20: =IF($A20="","",N($B20)*N($D20)) | G20: =IF($A20="","",N($E20)-N($F20)) | H20: =IF(N($E20)=0,"",N($G20)/N($E20)*100)
E21: =IF($A21="","",N($B21)*N($C21)) | F21: =IF($A21="","",N($B21)*N($D21)) | G21: =IF($A21="","",N($E21)-N($F21)) | H21: =IF(N($E21)=0,"",N($G21)/N($E21)*100)
E22: =IF($A22="","",N($B22)*N($C22)) | F22: =IF($A22="","",N($B22)*N($D22)) | G22: =IF($A22="","",N($E22)-N($F22)) | H22: =IF(N($E22)=0,"",N($G22)/N($E22)*100)
E23: =IF($A23="","",N($B23)*N($C23)) | F23: =IF($A23="","",N($B23)*N($D23)) | G23: =IF($A23="","",N($E23)-N($F23)) | H23: =IF(N($E23)=0,"",N($G23)/N($E23)*100)
... E38: =IF($A38="","",N($B38)*N($C38)) | F38: =IF($A38="","",N($B38)*N($D38)) | G38: =IF($A38="","",N($E38)-N($F38)) | H38: =IF(N($E38)=0,"",N($G38)/N($E38)*100)
A39: TOTAL | E39: =SUM(E9:E38) | F39: =SUM(F9:F38) | G39: =SUM(G9:G38) | H39: =IF($E39=0,"",$G39/$E39*100)
A41: CE QUE DISENT LES COMPTES — ما تقوله الحسابات
A42: Ventes de l'exercice (comptes 70) | C42: =-SUMIF('Balance'!$K$8:$K$192,"70",'Balance'!$G$8:$G$192)
A43: Stock initial de marchandises | C43: 300000
A44: Achats consommés (comptes 60) | C44: =SUMIF('Balance'!$K$8:$K$192,"60",'Balance'!$G$8:$G$192)
A45: Stock final de marchandises | C45: 260000
A46: Coût des marchandises vendues | C46: =N($C43)+N($C44)-N($C45)
A47: Marge brute | C47: =N($C42)-N($C46)
A48: Taux de marge | C48: =IF(N($C42)=0,"",N($C47)/N($C42)*100)
A50: Le SCF tient l'inventaire intermittent : le coût des marchandises vendues ne se constate pas vente par vente, il se déduit en fin d'exercice du stock initial, des achats et du stock final. Le tableau du haut est une estimation de gestion, celui du bas est le chiffre comptable. Les deux ne coïncident que si tout ce qui a été acheté a été vendu.

Sheet Compte de résultat
A1: COMPTE DE RÉSULTAT PAR NATURE
A2: حساب النتائج حسب الطبيعة
A3: =Societe&" · Exercice "&Exercice
A5: Présentation de l'arrêté du 26 juillet 2008, avec ses soldes intermédiaires de gestion.
B7: Rubrique | C7: التسمية | D7: Exercice
B8: Ventes et produits annexes | C8: المبيعات والمنتوجات الملحقة | D8: =-SUMIF('Balance'!$K$8:$K$192,"70",'Balance'!$G$8:$G$192)
B9: Variation stocks produits finis et en cours | C9: تغير مخزونات المنتجات التامة وقيد التنفيذ | D9: =-SUMIF('Balance'!$K$8:$K$192,"72",'Balance'!$G$8:$G$192)
B10: Production immobilisée | C10: الإنتاج المثبت | D10: =-SUMIF('Balance'!$K$8:$K$192,"73",'Balance'!$G$8:$G$192)
B11: Subventions d'exploitation | C11: إعانات الاستغلال | D11: =-SUMIF('Balance'!$K$8:$K$192,"74",'Balance'!$G$8:$G$192)
A12: I | B12: PRODUCTION DE L'EXERCICE | C12: إنتاج السنة المالية | D12: =SUM($D$8:$D$11)
B13: Achats consommés | C13: المشتريات المستهلكة | D13: =SUMIF('Balance'!$K$8:$K$192,"60",'Balance'!$G$8:$G$192)
B14: Services extérieurs et autres consommations | C14: الخدمات الخارجية والاستهلاكات الأخرى | D14: =SUMIF('Balance'!$K$8:$K$192,"61",'Balance'!$G$8:$G$192)+SUMIF('Balance'!$K$8:$K$192,"62",'Balance'!$G$8:$G$192)
A15: II | B15: CONSOMMATION DE L'EXERCICE | C15: استهلاكات السنة المالية | D15: =$D$13+$D$14
A16: III | B16: VALEUR AJOUTÉE D'EXPLOITATION | C16: القيمة المضافة للاستغلال | D16: =$D$12-$D$15
B17: Charges de personnel | C17: أعباء المستخدمين | D17: =SUMIF('Balance'!$K$8:$K$192,"63",'Balance'!$G$8:$G$192)
B18: Impôts, taxes et versements assimilés | C18: الضرائب والرسوم والمدفوعات المماثلة | D18: =SUMIF('Balance'!$K$8:$K$192,"64",'Balance'!$G$8:$G$192)
A19: IV | B19: EXCÉDENT BRUT D'EXPLOITATION | C19: الفائض الإجمالي عن الاستغلال | D19: =$D$16-$D$17-$D$18
B20: Autres produits opérationnels | C20: المنتوجات العملياتية الأخرى | D20: =-SUMIF('Balance'!$K$8:$K$192,"75",'Balance'!$G$8:$G$192)
B21: Autres charges opérationnelles | C21: الأعباء العملياتية الأخرى | D21: =SUMIF('Balance'!$K$8:$K$192,"65",'Balance'!$G$8:$G$192)
B22: Dotations aux amortissements, provisions et pertes de valeur | C22: مخصصات الاهتلاكات والمؤونات وخسائر القيمة | D22: =SUMIF('Balance'!$K$8:$K$192,"68",'Balance'!$G$8:$G$192)
B23: Reprise sur pertes de valeur et provisions | C23: استئناف خسائر القيمة والمؤونات | D23: =-SUMIF('Balance'!$K$8:$K$192,"78",'Balance'!$G$8:$G$192)
A24: V | B24: RÉSULTAT OPÉRATIONNEL | C24: النتيجة العملياتية | D24: =$D$19+$D$20-$D$21-$D$22+$D$23
B25: Produits financiers | C25: المنتوجات المالية | D25: =-SUMIF('Balance'!$K$8:$K$192,"76",'Balance'!$G$8:$G$192)
B26: Charges financières | C26: الأعباء المالية | D26: =SUMIF('Balance'!$K$8:$K$192,"66",'Balance'!$G$8:$G$192)
A27: VI | B27: RÉSULTAT FINANCIER | C27: النتيجة المالية | D27: =$D$25-$D$26
A28: VII | B28: RÉSULTAT ORDINAIRE AVANT IMPÔTS | C28: النتيجة العادية قبل الضرائب | D28: =$D$24+$D$27
B29: Impôts exigibles sur résultats ordinaires | C29: الضرائب الواجبة على النتائج العادية | D29: =SUMIF('Balance'!$L$8:$L$192,"695",'Balance'!$G$8:$G$192)+SUMIF('Balance'!$L$8:$L$192,"698",'Balance'!$G$8:$G$192)
B30: Impôts différés sur résultats ordinaires | C30: الضرائب المؤجلة على النتائج العادية | D30: =SUMIF('Balance'!$L$8:$L$192,"692",'Balance'!$G$8:$G$192)+SUMIF('Balance'!$L$8:$L$192,"693",'Balance'!$G$8:$G$192)
B31: TOTAL DES PRODUITS DES ACTIVITÉS ORDINAIRES | C31: مجموع منتوجات الأنشطة العادية | D31: =$D$8+$D$9+$D$10+$D$11+$D$20+$D$23+$D$25
B32: TOTAL DES CHARGES DES ACTIVITÉS ORDINAIRES | C32: مجموع أعباء الأنشطة العادية | D32: =$D$13+$D$14+$D$17+$D$18+$D$21+$D$22+$D$26+$D$29+$D$30
A33: VIII | B33: RÉSULTAT NET DES ACTIVITÉS ORDINAIRES | C33: النتيجة الصافية للأنشطة العادية | D33: =$D$31-$D$32
B34: Éléments extraordinaires — produits | C34: العناصر غير العادية — منتوجات | D34: =-SUMIF('Balance'!$K$8:$K$192,"77",'Balance'!$G$8:$G$192)
B35: Éléments extraordinaires — charges | C35: العناصر غير العادية — أعباء | D35: =SUMIF('Balance'!$K$8:$K$192,"67",'Balance'!$G$8:$G$192)
A36: IX | B36: RÉSULTAT NET DE L'EXERCICE | C36: النتيجة الصافية للسنة المالية | D36: =$D$33+$D$34-$D$35
A38: Les amortissements, les charges sociales et la variation de stock n'apparaissent que si vous les avez passés en écriture : ce document restitue le journal, il ne le complète pas.

Sheet Bilan
A1: BILAN
A2: الميزانية
A3: =Societe&" · Exercice "&Exercice
A5: Actif au brut, diminué des amortissements et des pertes de valeur. Passif au net. Le résultat de l'exercice vient du compte de résultat : aucune écriture de clôture n'est passée par ce classeur.
A7: ACTIF | B7: الأصول | C7: Brut | D7: Amort. / Prov. | E7: Net
A8: ACTIF NON COURANT | B8: الأصول غير الجارية
A9: Écart d'acquisition (goodwill) | B9: فارق الشراء | C9: =SUMIFS('Balance'!$G$8:$G$192,'Balance'!$H$8:$H$192,"AN_GW",'Balance'!$I$8:$I$192,0) | D9: =-SUMIFS('Balance'!$G$8:$G$192,'Balance'!$H$8:$H$192,"AN_GW",'Balance'!$I$8:$I$192,1) | E9: =$C9-$D9
A10: Immobilisations incorporelles | B10: التثبيتات المعنوية | C10: =SUMIFS('Balance'!$G$8:$G$192,'Balance'!$H$8:$H$192,"AN_INC",'Balance'!$I$8:$I$192,0) | D10: =-SUMIFS('Balance'!$G$8:$G$192,'Balance'!$H$8:$H$192,"AN_INC",'Balance'!$I$8:$I$192,1) | E10: =$C10-$D10
A11: Terrains | B11: الأراضي | C11: =SUMIFS('Balance'!$G$8:$G$192,'Balance'!$H$8:$H$192,"AN_TER",'Balance'!$I$8:$I$192,0) | D11: =-SUMIFS('Balance'!$G$8:$G$192,'Balance'!$H$8:$H$192,"AN_TER",'Balance'!$I$8:$I$192,1) | E11: =$C11-$D11
A12: Bâtiments | B12: المباني | C12: =SUMIFS('Balance'!$G$8:$G$192,'Balance'!$H$8:$H$192,"AN_BAT",'Balance'!$I$8:$I$192,0) | D12: =-SUMIFS('Balance'!$G$8:$G$192,'Balance'!$H$8:$H$192,"AN_BAT",'Balance'!$I$8:$I$192,1) | E12: =$C12-$D12
A13: Autres immobilisations corporelles | B13: تثبيتات عينية أخرى | C13: =SUMIFS('Balance'!$G$8:$G$192,'Balance'!$H$8:$H$192,"AN_AUT",'Balance'!$I$8:$I$192,0) | D13: =-SUMIFS('Balance'!$G$8:$G$192,'Balance'!$H$8:$H$192,"AN_AUT",'Balance'!$I$8:$I$192,1) | E13: =$C13-$D13
A14: Immobilisations en concession | B14: تثبيتات في شكل امتياز | C14: =SUMIFS('Balance'!$G$8:$G$192,'Balance'!$H$8:$H$192,"AN_CONC",'Balance'!$I$8:$I$192,0) | D14: =-SUMIFS('Balance'!$G$8:$G$192,'Balance'!$H$8:$H$192,"AN_CONC",'Balance'!$I$8:$I$192,1) | E14: =$C14-$D14
A15: Immobilisations en cours | B15: تثبيتات جاري إنجازها | C15: =SUMIFS('Balance'!$G$8:$G$192,'Balance'!$H$8:$H$192,"AN_ENC",'Balance'!$I$8:$I$192,0) | D15: =-SUMIFS('Balance'!$G$8:$G$192,'Balance'!$H$8:$H$192,"AN_ENC",'Balance'!$I$8:$I$192,1) | E15: =$C15-$D15
A16: Titres et participations | B16: السندات والمساهمات | C16: =SUMIFS('Balance'!$G$8:$G$192,'Balance'!$H$8:$H$192,"AN_FIN",'Balance'!$I$8:$I$192,0) | D16: =-SUMIFS('Balance'!$G$8:$G$192,'Balance'!$H$8:$H$192,"AN_FIN",'Balance'!$I$8:$I$192,1) | E16: =$C16-$D16
A17: Prêts et autres actifs financiers non courants | B17: قروض وأصول مالية أخرى غير جارية | C17: =SUMIFS('Balance'!$G$8:$G$192,'Balance'!$H$8:$H$192,"AN_PRET",'Balance'!$I$8:$I$192,0) | D17: =-SUMIFS('Balance'!$G$8:$G$192,'Balance'!$H$8:$H$192,"AN_PRET",'Balance'!$I$8:$I$192,1) | E17: =$C17-$D17
A18: Impôts différés actif | B18: الضرائب المؤجلة على الأصول | C18: =SUMIFS('Balance'!$G$8:$G$192,'Balance'!$H$8:$H$192,"AN_IDA",'Balance'!$I$8:$I$192,0) | D18: =-SUMIFS('Balance'!$G$8:$G$192,'Balance'!$H$8:$H$192,"AN_IDA",'Balance'!$I$8:$I$192,1) | E18: =$C18-$D18
A19: Total actif non courant | C19: =SUM(C9:C18) | D19: =SUM(D9:D18) | E19: =SUM(E9:E18)
A20: ACTIF COURANT | B20: الأصول الجارية
A21: Stocks et en-cours | B21: المخزونات والمنتجات قيد التنفيذ | C21: =SUMIFS('Balance'!$G$8:$G$192,'Balance'!$H$8:$H$192,"AC_STK",'Balance'!$I$8:$I$192,0) | D21: =-SUMIFS('Balance'!$G$8:$G$192,'Balance'!$H$8:$H$192,"AC_STK",'Balance'!$I$8:$I$192,1) | E21: =$C21-$D21
A22: Clients | B22: الزبائن | C22: =SUMIFS('Balance'!$G$8:$G$192,'Balance'!$H$8:$H$192,"AC_CLI",'Balance'!$I$8:$I$192,0) | D22: =-SUMIFS('Balance'!$G$8:$G$192,'Balance'!$H$8:$H$192,"AC_CLI",'Balance'!$I$8:$I$192,1) | E22: =$C22-$D22
A23: Autres débiteurs | B23: المدينون الآخرون | C23: =SUMIFS('Balance'!$G$8:$G$192,'Balance'!$H$8:$H$192,"AC_DEB",'Balance'!$I$8:$I$192,0) | D23: =-SUMIFS('Balance'!$G$8:$G$192,'Balance'!$H$8:$H$192,"AC_DEB",'Balance'!$I$8:$I$192,1) | E23: =$C23-$D23
A24: Impôts et assimilés | B24: الضرائب وما شابهها | C24: =SUMIFS('Balance'!$G$8:$G$192,'Balance'!$H$8:$H$192,"AC_IMP",'Balance'!$I$8:$I$192,0) | D24: =-SUMIFS('Balance'!$G$8:$G$192,'Balance'!$H$8:$H$192,"AC_IMP",'Balance'!$I$8:$I$192,1) | E24: =$C24-$D24
A25: Autres actifs courants | B25: أصول جارية أخرى | C25: =SUMIFS('Balance'!$G$8:$G$192,'Balance'!$H$8:$H$192,"AC_AUT",'Balance'!$I$8:$I$192,0) | D25: =-SUMIFS('Balance'!$G$8:$G$192,'Balance'!$H$8:$H$192,"AC_AUT",'Balance'!$I$8:$I$192,1) | E25: =$C25-$D25
A26: Placements et autres actifs financiers courants | B26: التوظيفات والأصول المالية الجارية الأخرى | C26: =SUMIFS('Balance'!$G$8:$G$192,'Balance'!$H$8:$H$192,"AC_PLA",'Balance'!$I$8:$I$192,0) | D26: =-SUMIFS('Balance'!$G$8:$G$192,'Balance'!$H$8:$H$192,"AC_PLA",'Balance'!$I$8:$I$192,1) | E26: =$C26-$D26
A27: Trésorerie | B27: الخزينة | C27: =SUMIFS('Balance'!$G$8:$G$192,'Balance'!$H$8:$H$192,"AC_TRE",'Balance'!$I$8:$I$192,0) | D27: =-SUMIFS('Balance'!$G$8:$G$192,'Balance'!$H$8:$H$192,"AC_TRE",'Balance'!$I$8:$I$192,1) | E27: =$C27-$D27
A28: Total actif courant | C28: =SUM(C21:C27) | D28: =SUM(D21:D27) | E28: =SUM(E21:E27)
A29: TOTAL ACTIF | B29: مجموع الأصول | C29: =C19+C28 | D29: =D19+D28 | E29: =E19+E28
A31: PASSIF | B31: الخصوم | E31: Net
A32: CAPITAUX PROPRES | B32: رؤوس الأموال الخاصة
A33: Capital émis | B33: رأس المال الصادر | E33: =-SUMIFS('Balance'!$G$8:$G$192,'Balance'!$H$8:$H$192,"CP_CAP")
A34: Capital non appelé | B34: رأس المال غير المستدعى | E34: =-SUMIFS('Balance'!$G$8:$G$192,'Balance'!$H$8:$H$192,"CP_NAP")
A35: Primes et réserves — réserves consolidées | B35: العلاوات والاحتياطات | E35: =-SUMIFS('Balance'!$G$8:$G$192,'Balance'!$H$8:$H$192,"CP_PRI")
A36: Écarts de réévaluation | B36: فوارق إعادة التقييم | E36: =-SUMIFS('Balance'!$G$8:$G$192,'Balance'!$H$8:$H$192,"CP_REE")
A37: Écart d'équivalence | B37: فارق المعادلة | E37: =-SUMIFS('Balance'!$G$8:$G$192,'Balance'!$H$8:$H$192,"CP_EQU")
A38: Résultat net (résultat de l'exercice) | B38: النتيجة الصافية (نتيجة السنة المالية) | E38: =-SUMIFS('Balance'!$G$8:$G$192,'Balance'!$H$8:$H$192,"CP_RES")+'Compte de résultat'!$D$36
A39: Autres capitaux propres — report à nouveau | B39: رؤوس أموال خاصة أخرى — الترحيل من جديد | E39: =-SUMIFS('Balance'!$G$8:$G$192,'Balance'!$H$8:$H$192,"CP_ART")
A40: Total capitaux propres | E40: =SUM(E33:E39)
A41: PASSIFS NON COURANTS | B41: الخصوم غير الجارية
A42: Emprunts et dettes financières | B42: القروض والديون المالية | E42: =-SUMIFS('Balance'!$G$8:$G$192,'Balance'!$H$8:$H$192,"PN_EMP")
A43: Impôts (différés et provisionnés) | B43: الضرائب (المؤجلة والمرصود لها) | E43: =-SUMIFS('Balance'!$G$8:$G$192,'Balance'!$H$8:$H$192,"PN_IDP")
A44: Autres dettes non courantes | B44: ديون أخرى غير جارية | E44: =-SUMIFS('Balance'!$G$8:$G$192,'Balance'!$H$8:$H$192,"PN_AUT")
A45: Provisions et produits constatés d'avance | B45: المؤونات والمنتوجات المثبتة مسبقا | E45: =-SUMIFS('Balance'!$G$8:$G$192,'Balance'!$H$8:$H$192,"PN_PRO")
A46: Total passifs non courants | E46: =SUM(E42:E45)
A47: PASSIFS COURANTS | B47: الخصوم الجارية
A48: Fournisseurs et comptes rattachés | B48: الموردون والحسابات الملحقة | E48: =-SUMIFS('Balance'!$G$8:$G$192,'Balance'!$H$8:$H$192,"PC_FRN")
A49: Impôts | B49: الضرائب | E49: =-SUMIFS('Balance'!$G$8:$G$192,'Balance'!$H$8:$H$192,"PC_IMP")
A50: Autres dettes | B50: ديون أخرى | E50: =-SUMIFS('Balance'!$G$8:$G$192,'Balance'!$H$8:$H$192,"PC_AUT")
A51: Trésorerie passif | B51: خزينة الخصوم | E51: =-SUMIFS('Balance'!$G$8:$G$192,'Balance'!$H$8:$H$192,"PC_TRE")
A52: Total passifs courants | E52: =SUM(E48:E51)
A53: TOTAL PASSIF | B53: مجموع الخصوم | E53: =E40+E46+E52
A55: =IF(ROUND($E$29-$E$53,2)=0,"Bilan équilibré : total actif = total passif.","Écart de "&TEXT($E$29-$E$53,"#,##0.00")&" DA entre l'actif et le passif — vérifiez le journal.")

Sheet Rapports
A1: RAPPORTS
A2: التقارير
A3: =Societe&" · Exercice "&Exercice
A5: TVA, trésorerie, tiers, charges par nature, résultat par centre de coût. Tout est déduit du journal.
A7: TVA — الرسم على القيمة المضافة
A8: TVA collectée (4457) | B8: الرسم المحصل | C8: =-SUMIF('Balance'!$A$8:$A$192,"4457",'Balance'!$G$8:$G$192)
A9: TVA déductible sur biens et services (44566) | B9: الرسم القابل للخصم — سلع وخدمات | C9: =SUMIF('Balance'!$A$8:$A$192,"44566",'Balance'!$G$8:$G$192)
A10: TVA déductible sur immobilisations (44562) | B10: الرسم القابل للخصم — تثبيتات | C10: =SUMIF('Balance'!$A$8:$A$192,"44562",'Balance'!$G$8:$G$192)
A11: TVA à décaisser | B11: الرسم الواجب دفعه | C11: =MAX(0,C8-C9-C10)
A12: Précompte TVA reporté | B12: الرصيد المرحل | C12: =MAX(0,C9+C10-C8)
A13: Droit de timbre encaissé (442) | B13: رسم الطابع المحصل | C13: =-SUMIF('Balance'!$A$8:$A$192,"442",'Balance'!$G$8:$G$192)
A15: TRÉSORERIE — الخزينة
A16: Caisse (530) | B16: الصندوق | C16: =SUMIF('Balance'!$A$8:$A$192,"530",'Balance'!$G$8:$G$192)
A17: Banque (512) | B17: البنك | C17: =SUMIF('Balance'!$A$8:$A$192,"512",'Balance'!$G$8:$G$192)
A18: CCP (515) | B18: الحساب الجاري البريدي | C18: =SUMIF('Balance'!$A$8:$A$192,"515",'Balance'!$G$8:$G$192)
A19: Total disponible | B19: مجموع المتاح | C19: =SUM(C16:C18)
A21: TIERS — الأغيار
A22: Clients (411) — solde débiteur | B22: الزبائن | C22: =SUMIF('Balance'!$A$8:$A$192,"411",'Balance'!$G$8:$G$192)
A23: Fournisseurs (401) — solde créditeur | B23: الموردون | C23: =-SUMIF('Balance'!$A$8:$A$192,"401",'Balance'!$G$8:$G$192)
A24: Personnel (421) | B24: المستخدمون | C24: =-SUMIF('Balance'!$A$8:$A$192,"421",'Balance'!$G$8:$G$192)
A25: Organismes sociaux (431) | B25: الهيئات الاجتماعية | C25: =-SUMIF('Balance'!$A$8:$A$192,"431",'Balance'!$G$8:$G$192)
A27: CHARGES PAR NATURE — الأعباء حسب الطبيعة
A28: 60 — Achats consommés | B28: المشتريات المستهلكة | C28: =SUMIF('Balance'!$K$8:$K$192,"60",'Balance'!$G$8:$G$192)
A29: 61 — Services extérieurs | B29: الخدمات الخارجية | C29: =SUMIF('Balance'!$K$8:$K$192,"61",'Balance'!$G$8:$G$192)
A30: 62 — Autres services extérieurs | B30: الخدمات الخارجية الأخرى | C30: =SUMIF('Balance'!$K$8:$K$192,"62",'Balance'!$G$8:$G$192)
A31: 63 — Charges de personnel | B31: أعباء المستخدمين | C31: =SUMIF('Balance'!$K$8:$K$192,"63",'Balance'!$G$8:$G$192)
A32: 64 — Impôts et taxes | B32: الضرائب والرسوم | C32: =SUMIF('Balance'!$K$8:$K$192,"64",'Balance'!$G$8:$G$192)
A33: 65 — Autres charges opérationnelles | B33: الأعباء العملياتية الأخرى | C33: =SUMIF('Balance'!$K$8:$K$192,"65",'Balance'!$G$8:$G$192)
A34: 66 — Charges financières | B34: الأعباء المالية | C34: =SUMIF('Balance'!$K$8:$K$192,"66",'Balance'!$G$8:$G$192)
A35: 68 — Dotations | B35: المخصصات | C35: =SUMIF('Balance'!$K$8:$K$192,"68",'Balance'!$G$8:$G$192)
A36: Total des charges | B36: مجموع الأعباء | C36: =SUM(C28:C35)
A38: RÉSULTAT PAR CENTRE DE COÛT — النتيجة حسب مركز التكلفة
A39: Centre | B39: Produits | C39: Charges | D39: Résultat
A40: =IF('Centres de coûts'!$A$8="","",'Centres de coûts'!$A$8&" "&'Centres de coûts'!$B$8) | B40: =IF('Centres de coûts'!$A$8="","",-SUMPRODUCT(('Journal'!$G$8:$G$2007='Centres de coûts'!$A$8)*(LEFT('Journal'!$D$8:$D$2007,1)="7")*('Journal'!$H$8:$H$2007-'Journal'!$I$8:$I$2007))) | C40: =IF('Centres de coûts'!$A$8="","",SUMPRODUCT(('Journal'!$G$8:$G$2007='Centres de coûts'!$A$8)*(LEFT('Journal'!$D$8:$D$2007,1)="6")*('Journal'!$H$8:$H$2007-'Journal'!$I$8:$I$2007))) | D40: =IF('Centres de coûts'!$A$8="","",N($B40)-N($C40))
A41: =IF('Centres de coûts'!$A$9="","",'Centres de coûts'!$A$9&" "&'Centres de coûts'!$B$9) | B41: =IF('Centres de coûts'!$A$9="","",-SUMPRODUCT(('Journal'!$G$8:$G$2007='Centres de coûts'!$A$9)*(LEFT('Journal'!$D$8:$D$2007,1)="7")*('Journal'!$H$8:$H$2007-'Journal'!$I$8:$I$2007))) | C41: =IF('Centres de coûts'!$A$9="","",SUMPRODUCT(('Journal'!$G$8:$G$2007='Centres de coûts'!$A$9)*(LEFT('Journal'!$D$8:$D$2007,1)="6")*('Journal'!$H$8:$H$2007-'Journal'!$I$8:$I$2007))) | D41: =IF('Centres de coûts'!$A$9="","",N($B41)-N($C41))
A42: =IF('Centres de coûts'!$A$10="","",'Centres de coûts'!$A$10&" "&'Centres de coûts'!$B$10) | B42: =IF('Centres de coûts'!$A$10="","",-SUMPRODUCT(('Journal'!$G$8:$G$2007='Centres de coûts'!$A$10)*(LEFT('Journal'!$D$8:$D$2007,1)="7")*('Journal'!$H$8:$H$2007-'Journal'!$I$8:$I$2007))) | C42: =IF('Centres de coûts'!$A$10="","",SUMPRODUCT(('Journal'!$G$8:$G$2007='Centres de coûts'!$A$10)*(LEFT('Journal'!$D$8:$D$2007,1)="6")*('Journal'!$H$8:$H$2007-'Journal'!$I$8:$I$2007))) | D42: =IF('Centres de coûts'!$A$10="","",N($B42)-N($C42))
A43: =IF('Centres de coûts'!$A$11="","",'Centres de coûts'!$A$11&" "&'Centres de coûts'!$B$11) | B43: =IF('Centres de coûts'!$A$11="","",-SUMPRODUCT(('Journal'!$G$8:$G$2007='Centres de coûts'!$A$11)*(LEFT('Journal'!$D$8:$D$2007,1)="7")*('Journal'!$H$8:$H$2007-'Journal'!$I$8:$I$2007))) | C43: =IF('Centres de coûts'!$A$11="","",SUMPRODUCT(('Journal'!$G$8:$G$2007='Centres de coûts'!$A$11)*(LEFT('Journal'!$D$8:$D$2007,1)="6")*('Journal'!$H$8:$H$2007-'Journal'!$I$8:$I$2007))) | D43: =IF('Centres de coûts'!$A$11="","",N($B43)-N($C43))
A44: =IF('Centres de coûts'!$A$12="","",'Centres de coûts'!$A$12&" "&'Centres de coûts'!$B$12) | B44: =IF('Centres de coûts'!$A$12="","",-SUMPRODUCT(('Journal'!$G$8:$G$2007='Centres de coûts'!$A$12)*(LEFT('Journal'!$D$8:$D$2007,1)="7")*('Journal'!$H$8:$H$2007-'Journal'!$I$8:$I$2007))) | C44: =IF('Centres de coûts'!$A$12="","",SUMPRODUCT(('Journal'!$G$8:$G$2007='Centres de coûts'!$A$12)*(LEFT('Journal'!$D$8:$D$2007,1)="6")*('Journal'!$H$8:$H$2007-'Journal'!$I$8:$I$2007))) | D44: =IF('Centres de coûts'!$A$12="","",N($B44)-N($C44))
A45: =IF('Centres de coûts'!$A$13="","",'Centres de coûts'!$A$13&" "&'Centres de coûts'!$B$13) | B45: =IF('Centres de coûts'!$A$13="","",-SUMPRODUCT(('Journal'!$G$8:$G$2007='Centres de coûts'!$A$13)*(LEFT('Journal'!$D$8:$D$2007,1)="7")*('Journal'!$H$8:$H$2007-'Journal'!$I$8:$I$2007))) | C45: =IF('Centres de coûts'!$A$13="","",SUMPRODUCT(('Journal'!$G$8:$G$2007='Centres de coûts'!$A$13)*(LEFT('Journal'!$D$8:$D$2007,1)="6")*('Journal'!$H$8:$H$2007-'Journal'!$I$8:$I$2007))) | D45: =IF('Centres de coûts'!$A$13="","",N($B45)-N($C45))
A46: =IF('Centres de coûts'!$A$14="","",'Centres de coûts'!$A$14&" "&'Centres de coûts'!$B$14) | B46: =IF('Centres de coûts'!$A$14="","",-SUMPRODUCT(('Journal'!$G$8:$G$2007='Centres de coûts'!$A$14)*(LEFT('Journal'!$D$8:$D$2007,1)="7")*('Journal'!$H$8:$H$2007-'Journal'!$I$8:$I$2007))) | C46: =IF('Centres de coûts'!$A$14="","",SUMPRODUCT(('Journal'!$G$8:$G$2007='Centres de coûts'!$A$14)*(LEFT('Journal'!$D$8:$D$2007,1)="6")*('Journal'!$H$8:$H$2007-'Journal'!$I$8:$I$2007))) | D46: =IF('Centres de coûts'!$A$14="","",N($B46)-N($C46))
A47: =IF('Centres de coûts'!$A$15="","",'Centres de coûts'!$A$15&" "&'Centres de coûts'!$B$15) | B47: =IF('Centres de coûts'!$A$15="","",-SUMPRODUCT(('Journal'!$G$8:$G$2007='Centres de coûts'!$A$15)*(LEFT('Journal'!$D$8:$D$2007,1)="7")*('Journal'!$H$8:$H$2007-'Journal'!$I$8:$I$2007))) | C47: =IF('Centres de coûts'!$A$15="","",SUMPRODUCT(('Journal'!$G$8:$G$2007='Centres de coûts'!$A$15)*(LEFT('Journal'!$D$8:$D$2007,1)="6")*('Journal'!$H$8:$H$2007-'Journal'!$I$8:$I$2007))) | D47: =IF('Centres de coûts'!$A$15="","",N($B47)-N($C47))
A48: =IF('Centres de coûts'!$A$16="","",'Centres de coûts'!$A$16&" "&'Centres de coûts'!$B$16) | B48: =IF('Centres de coûts'!$A$16="","",-SUMPRODUCT(('Journal'!$G$8:$G$2007='Centres de coûts'!$A$16)*(LEFT('Journal'!$D$8:$D$2007,1)="7")*('Journal'!$H$8:$H$2007-'Journal'!$I$8:$I$2007))) | C48: =IF('Centres de coûts'!$A$16="","",SUMPRODUCT(('Journal'!$G$8:$G$2007='Centres de coûts'!$A$16)*(LEFT('Journal'!$D$8:$D$2007,1)="6")*('Journal'!$H$8:$H$2007-'Journal'!$I$8:$I$2007))) | D48: =IF('Centres de coûts'!$A$16="","",N($B48)-N($C48))
A49: =IF('Centres de coûts'!$A$17="","",'Centres de coûts'!$A$17&" "&'Centres de coûts'!$B$17) | B49: =IF('Centres de coûts'!$A$17="","",-SUMPRODUCT(('Journal'!$G$8:$G$2007='Centres de coûts'!$A$17)*(LEFT('Journal'!$D$8:$D$2007,1)="7")*('Journal'!$H$8:$H$2007-'Journal'!$I$8:$I$2007))) | C49: =IF('Centres de coûts'!$A$17="","",SUMPRODUCT(('Journal'!$G$8:$G$2007='Centres de coûts'!$A$17)*(LEFT('Journal'!$D$8:$D$2007,1)="6")*('Journal'!$H$8:$H$2007-'Journal'!$I$8:$I$2007))) | D49: =IF('Centres de coûts'!$A$17="","",N($B49)-N($C49))
A50: =IF('Centres de coûts'!$A$18="","",'Centres de coûts'!$A$18&" "&'Centres de coûts'!$B$18) | B50: =IF('Centres de coûts'!$A$18="","",-SUMPRODUCT(('Journal'!$G$8:$G$2007='Centres de coûts'!$A$18)*(LEFT('Journal'!$D$8:$D$2007,1)="7")*('Journal'!$H$8:$H$2007-'Journal'!$I$8:$I$2007))) | C50: =IF('Centres de coûts'!$A$18="","",SUMPRODUCT(('Journal'!$G$8:$G$2007='Centres de coûts'!$A$18)*(LEFT('Journal'!$D$8:$D$2007,1)="6")*('Journal'!$H$8:$H$2007-'Journal'!$I$8:$I$2007))) | D50: =IF('Centres de coûts'!$A$18="","",N($B50)-N($C50))
A51: =IF('Centres de coûts'!$A$19="","",'Centres de coûts'!$A$19&" "&'Centres de coûts'!$B$19) | B51: =IF('Centres de coûts'!$A$19="","",-SUMPRODUCT(('Journal'!$G$8:$G$2007='Centres de coûts'!$A$19)*(LEFT('Journal'!$D$8:$D$2007,1)="7")*('Journal'!$H$8:$H$2007-'Journal'!$I$8:$I$2007))) | C51: =IF('Centres de coûts'!$A$19="","",SUMPRODUCT(('Journal'!$G$8:$G$2007='Centres de coûts'!$A$19)*(LEFT('Journal'!$D$8:$D$2007,1)="6")*('Journal'!$H$8:$H$2007-'Journal'!$I$8:$I$2007))) | D51: =IF('Centres de coûts'!$A$19="","",N($B51)-N($C51))
A52: =IF('Centres de coûts'!$A$20="","",'Centres de coûts'!$A$20&" "&'Centres de coûts'!$B$20) | B52: =IF('Centres de coûts'!$A$20="","",-SUMPRODUCT(('Journal'!$G$8:$G$2007='Centres de coûts'!$A$20)*(LEFT('Journal'!$D$8:$D$2007,1)="7")*('Journal'!$H$8:$H$2007-'Journal'!$I$8:$I$2007))) | C52: =IF('Centres de coûts'!$A$20="","",SUMPRODUCT(('Journal'!$G$8:$G$2007='Centres de coûts'!$A$20)*(LEFT('Journal'!$D$8:$D$2007,1)="6")*('Journal'!$H$8:$H$2007-'Journal'!$I$8:$I$2007))) | D52: =IF('Centres de coûts'!$A$20="","",N($B52)-N($C52))
A53: =IF('Centres de coûts'!$A$21="","",'Centres de coûts'!$A$21&" "&'Centres de coûts'!$B$21) | B53: =IF('Centres de coûts'!$A$21="","",-SUMPRODUCT(('Journal'!$G$8:$G$2007='Centres de coûts'!$A$21)*(LEFT('Journal'!$D$8:$D$2007,1)="7")*('Journal'!$H$8:$H$2007-'Journal'!$I$8:$I$2007))) | C53: =IF('Centres de coûts'!$A$21="","",SUMPRODUCT(('Journal'!$G$8:$G$2007='Centres de coûts'!$A$21)*(LEFT('Journal'!$D$8:$D$2007,1)="6")*('Journal'!$H$8:$H$2007-'Journal'!$I$8:$I$2007))) | D53: =IF('Centres de coûts'!$A$21="","",N($B53)-N($C53))
A54: =IF('Centres de coûts'!$A$22="","",'Centres de coûts'!$A$22&" "&'Centres de coûts'!$B$22) | B54: =IF('Centres de coûts'!$A$22="","",-SUMPRODUCT(('Journal'!$G$8:$G$2007='Centres de coûts'!$A$22)*(LEFT('Journal'!$D$8:$D$2007,1)="7")*('Journal'!$H$8:$H$2007-'Journal'!$I$8:$I$2007))) | C54: =IF('Centres de coûts'!$A$22="","",SUMPRODUCT(('Journal'!$G$8:$G$2007='Centres de coûts'!$A$22)*(LEFT('Journal'!$D$8:$D$2007,1)="6")*('Journal'!$H$8:$H$2007-'Journal'!$I$8:$I$2007))) | D54: =IF('Centres de coûts'!$A$22="","",N($B54)-N($C54))
A55: =IF('Centres de coûts'!$A$23="","",'Centres de coûts'!$A$23&" "&'Centres de coûts'!$B$23) | B55: =IF('Centres de coûts'!$A$23="","",-SUMPRODUCT(('Journal'!$G$8:$G$2007='Centres de coûts'!$A$23)*(LEFT('Journal'!$D$8:$D$2007,1)="7")*('Journal'!$H$8:$H$2007-'Journal'!$I$8:$I$2007))) | C55: =IF('Centres de coûts'!$A$23="","",SUMPRODUCT(('Journal'!$G$8:$G$2007='Centres de coûts'!$A$23)*(LEFT('Journal'!$D$8:$D$2007,1)="6")*('Journal'!$H$8:$H$2007-'Journal'!$I$8:$I$2007))) | D55: =IF('Centres de coûts'!$A$23="","",N($B55)-N($C55))
A56: =IF('Centres de coûts'!$A$24="","",'Centres de coûts'!$A$24&" "&'Centres de coûts'!$B$24) | B56: =IF('Centres de coûts'!$A$24="","",-SUMPRODUCT(('Journal'!$G$8:$G$2007='Centres de coûts'!$A$24)*(LEFT('Journal'!$D$8:$D$2007,1)="7")*('Journal'!$H$8:$H$2007-'Journal'!$I$8:$I$2007))) | C56: =IF('Centres de coûts'!$A$24="","",SUMPRODUCT(('Journal'!$G$8:$G$2007='Centres de coûts'!$A$24)*(LEFT('Journal'!$D$8:$D$2007,1)="6")*('Journal'!$H$8:$H$2007-'Journal'!$I$8:$I$2007))) | D56: =IF('Centres de coûts'!$A$24="","",N($B56)-N($C56))
A57: =IF('Centres de coûts'!$A$25="","",'Centres de coûts'!$A$25&" "&'Centres de coûts'!$B$25) | B57: =IF('Centres de coûts'!$A$25="","",-SUMPRODUCT(('Journal'!$G$8:$G$2007='Centres de coûts'!$A$25)*(LEFT('Journal'!$D$8:$D$2007,1)="7")*('Journal'!$H$8:$H$2007-'Journal'!$I$8:$I$2007))) | C57: =IF('Centres de coûts'!$A$25="","",SUMPRODUCT(('Journal'!$G$8:$G$2007='Centres de coûts'!$A$25)*(LEFT('Journal'!$D$8:$D$2007,1)="6")*('Journal'!$H$8:$H$2007-'Journal'!$I$8:$I$2007))) | D57: =IF('Centres de coûts'!$A$25="","",N($B57)-N($C57))
A58: =IF('Centres de coûts'!$A$26="","",'Centres de coûts'!$A$26&" "&'Centres de coûts'!$B$26) | B58: =IF('Centres de coûts'!$A$26="","",-SUMPRODUCT(('Journal'!$G$8:$G$2007='Centres de coûts'!$A$26)*(LEFT('Journal'!$D$8:$D$2007,1)="7")*('Journal'!$H$8:$H$2007-'Journal'!$I$8:$I$2007))) | C58: =IF('Centres de coûts'!$A$26="","",SUMPRODUCT(('Journal'!$G$8:$G$2007='Centres de coûts'!$A$26)*(LEFT('Journal'!$D$8:$D$2007,1)="6")*('Journal'!$H$8:$H$2007-'Journal'!$I$8:$I$2007))) | D58: =IF('Centres de coûts'!$A$26="","",N($B58)-N($C58))
A59: =IF('Centres de coûts'!$A$27="","",'Centres de coûts'!$A$27&" "&'Centres de coûts'!$B$27) | B59: =IF('Centres de coûts'!$A$27="","",-SUMPRODUCT(('Journal'!$G$8:$G$2007='Centres de coûts'!$A$27)*(LEFT('Journal'!$D$8:$D$2007,1)="7")*('Journal'!$H$8:$H$2007-'Journal'!$I$8:$I$2007))) | C59: =IF('Centres de coûts'!$A$27="","",SUMPRODUCT(('Journal'!$G$8:$G$2007='Centres de coûts'!$A$27)*(LEFT('Journal'!$D$8:$D$2007,1)="6")*('Journal'!$H$8:$H$2007-'Journal'!$I$8:$I$2007))) | D59: =IF('Centres de coûts'!$A$27="","",N($B59)-N($C59))
A61: Une ligne du journal sans centre n'apparaît dans aucune de ces lignes : la somme des centres est inférieure au résultat de l'exercice tant que tout n'est pas affecté.
